{"result":{"story":{"inappropriateContentFlaggers":[],"editedAt":{"__type":"Date","iso":"2018-11-21T13:24:01.755Z"},"searchTerms":["5","b","br","bro","brot","broth","brothe","brother","e","ep","epi","epis","episo","episod","episode","f","fi","fia","fian","fianc","fiance","fiances","m","my","r","ro","ros","rosa","rosal","rosali","rosalin","rosalina","rosalinas","rosalinasa","rosalinasan","rosalinasant","rosalinasanti","rosalinasantia","rosalinasantiag","rosalinasantiago","s","sa","san"],"tags":[""],"authors":[{"__type":"Pointer","className":"Author","objectId":"Y8zMHCQWhK"}],"characters":[{"name":"Jonathan","createdAt":"2018-06-15T20:52:53.009Z","updatedAt":"2018-06-15T20:52:53.009Z","objectId":"6qyHe27abt","__type":"Object","className":"Character"},{"name":"Taylor","createdAt":"2018-06-15T20:52:53.145Z","updatedAt":"2018-11-15T21:39:57.958Z","main":true,"aclUpdatedAt":{"__type":"Date","iso":"2018-11-15T21:39:57.950Z"},"ACL":{"*":{"read":true},"ODNHPL0tEx":{"write":true}},"objectId":"wpLMHTKAhB","__type":"Object","className":"Character"},{"name":"Blake","createdAt":"2018-06-15T20:52:53.285Z","updatedAt":"2018-06-15T20:52:53.285Z","objectId":"Mykb1lr5RY","__type":"Object","className":"Character"},{"name":"Mom","createdAt":"2018-06-15T20:52:53.423Z","updatedAt":"2018-06-15T20:52:53.423Z","objectId":"kpAqufNrCW","__type":"Object","className":"Character"},{"name":"separator","createdAt":"2018-06-15T20:52:53.558Z","updatedAt":"2018-06-15T20:52:53.558Z","objectId":"3eG6Gw0F7D","__type":"Object","className":"Character"}],"uid":"myfiancesbrother-5","hidden":false,"title":"My Fiance's Brother - Episode 5","seriesTitle":"My Fiance's Brother","lang":"en","canonicalTitle":"my fiance's brother","storyDescription":"Taylor is marrying her best friend’s brother. But then her best friend confesses he’s in love with her… ","trackMessage":false,"editorsChoice":false,"teaser":false,"createdOutsideApp":true,"creator":"web-uploader","pendingDeletion":false,"inappropriateContent":false,"seriesTitleAutoGenerated":true,"alreadyPublished":true,"risk":-1,"wordCount":693,"seriesIdentifier":"d44f14ca-cd7e-50fd-866b-c92d74c1452f","category":{"__type":"Pointer","className":"Genre","objectId":"PE8id6J1mi"},"episodeIndex":5,"episodeSeriesName":"Episode 5","episodeTitle":"Episode 5","episodeCount":10,"author":{"autoFolloweesFollowers":[],"username":"RosalinaSanTiago","lastName":"San","firstName":"Rosalina","fullName":"Rosalina San Tiago","bio":"Cecy Robson writing as Rosalina San Tiago is an author of contemporary romance, young adult adventure, and award-winning urban fantasy. ","profilePictureSmall":{"__type":"File","name":"87106c3b25228a306277b2da41d7144a_241-small.jpg","url":"https://d3b7s6bg6ueiky.cloudfront.net/87106c3b25228a306277b2da41d7144a_241-small.jpg"},"profilePictureMedium":{"__type":"File","name":"c7adbf14ecf3bf6d00dbe4f5ce4caadc_241-medium.jpg","url":"https://d3b7s6bg6ueiky.cloudfront.net/c7adbf14ecf3bf6d00dbe4f5ce4caadc_241-medium.jpg"},"createdAt":"2017-11-16T20:40:29.972Z","updatedAt":"2018-11-22T23:00:16.282Z","usernameUpdatedAt":{"__type":"Date","iso":"2017-11-16T20:40:30.080Z"},"canonicalUsername":"rosalinasantiago","writeCount":9,"lastUpdateMetrics":{"__type":"Date","iso":"2018-11-10T06:44:00.126Z"},"loveCount":0,"readCount":0,"followerCount":2,"followingCount":0,"writtenStoryReadingRightsUntil":{"__type":"Date","iso":"2018-11-28T21:44:39.885Z"},"lastNotificationCreatedAt":{"__type":"Date","iso":"2018-11-22T23:00:16.273Z"},"ACL":{"*":{"read":true},"ODNHPL0tEx":{"read":true,"write":true}},"objectId":"ODNHPL0tEx","__type":"Object","className":"_User"},"recommendable":false,"searchable":true,"readable":true,"country":"en","genre":"Romance","group":2,"createdAt":"2018-06-15T20:52:54.569Z","updatedAt":"2018-12-05T06:22:21.587Z","aclUpdatedAt":{"__type":"Date","iso":"2018-06-15T20:52:54.623Z"},"scoreUpdatedAt":{"__type":"Date","iso":"2018-12-05T06:05:00.028Z"},"previousReadVelocity":116,"readVelocity":118,"readAcceleration":2,"lastUpdateMetrics":{"__type":"Date","iso":"2018-11-26T17:00:04.127Z"},"sampleLovers":[],"readCount":3664,"i18n":"fr,es,de,ja,ko,pt,it,ar,no","prePaywallNotification":"Oh no—Taylor is bleeding 😢 Tap back into Hooked to see if she’s okay.","postPaywallNotification":"The secret’s out—now all the hidden relationships are out in the open. But will Taylor and Blake be able to heal? ❤️ Tap back into Hooked to find out.","completionData":{"episode":{"all":{"started":4112,"completed":3714,"completionRate":90.32101167315174},"ios":{"started":3300,"completed":3164,"completionRate":95.87878787878788},"android":{"started":812,"completed":550,"completionRate":67.73399014778325}},"series":{"all":{"completionRate":40.153810300629225,"completionRateAfterEpisodeThree":47.06362153344209},"ios":{"completionRate":41.46001671774868,"completionRateAfterEpisodeThree":47.85455558651435},"android":{"completionRate":33.47578347578347,"completionRateAfterEpisodeThree":43.01994301994302}}},"completionDataUpdatedAt":{"__type":"Date","iso":"2018-12-05T05:50:04.816Z"},"style":"{\"theme\":\"watcher\",\"backgroundColor\":\"#c6cadc\",\"cover\":{\"isGradientVisible\":true,\"gradientOpacity\":0.5},\"messages\":{\"backgroundColor\":\"#f6f7f8\",\"borderColor\":\"#f6f7f8\",\"senderFontName\":\"AvenirNext-Bold\",\"senderFontSize\":16,\"textFontName\":\"Optima-Regular\",\"characterColors\":[\"#1A6B55\",\"#8C332B\",\"#23598C\",\"#0C8983\"],\"textColors\":[\"#2A3341\",\"#2A3341\",\"#2A3341\",\"#2A3341\"],\"nonAttributedTextFontName\":\"Optima-Regular\",\"nonAttributedTextColor\":\"#2a3341\",\"nonAttributedBackgroundColor\":\"#c6cadc\",\"nonAttributedBorderColor\":\"#c6cadc\",\"separator\":{\"textColor\":\"#2a3341\"}}}","started_ios":3295,"completed_ios":3132,"loveRatio":0.0013646288209606986,"commentRatio":0,"visibleInNew":false,"coverImageFile":{"__type":"File","name":"a0571dd4818e8aec4a2f30b76b234a45_myfiancesbrother-cover-v1.jpg","url":"https://d3b7s6bg6ueiky.cloudfront.net/a0571dd4818e8aec4a2f30b76b234a45_myfiancesbrother-cover-v1.jpg"},"coverImageThumbnailFile":{"__type":"File","name":"445164eb3448e7ceca90c46030efcefc_4902-thumbnail.jpg","url":"https://d3b7s6bg6ueiky.cloudfront.net/445164eb3448e7ceca90c46030efcefc_4902-thumbnail.jpg"},"coverImageLoRes":{"__type":"File","name":"b3f2370146d7fd2ecda88c58feee656f_4902-thumbnail-lores.jpg","url":"https://d3b7s6bg6ueiky.cloudfront.net/b3f2370146d7fd2ecda88c58feee656f_4902-thumbnail-lores.jpg"},"teaserVideoUrl":"http://dvgf17xr8ms83.cloudfront.net/486xeSW4xD/video_5bf4d2ca8ad55.mov","started_android":810,"searchTermsUpdatedAt":{"__type":"Date","iso":"2018-12-05T03:33:00.558Z"},"completed_android":527,"loveCount":5,"ACL":{"*":{"read":true},"ODNHPL0tEx":{"write":true}},"objectId":"oKOWCyIHxC","__type":"Object","className":"Story"},"messages":[{"text":"Taylor waits alone in the hospital room.","ordinalInStory":1,"mediaWidth":null,"mediaHeight":null,"isTypingIntroDuration":0,"story":{"__type":"Pointer","className":"Story","objectId":"oKOWCyIHxC"},"risk":2,"createdAt":"2018-06-15T20:52:54.902Z","updatedAt":"2018-06-15T20:52:55.004Z","aclUpdatedAt":{"__type":"Date","iso":"2018-06-15T20:52:54.983Z"},"ACL":{"*":{"read":true},"ODNHPL0tEx":{"write":true}},"objectId":"qK7mqmBCJI","__type":"Object","className":"Message"},{"text":"The white sterile sheets are gathered tightly against her belly.","ordinalInStory":2,"mediaWidth":null,"mediaHeight":null,"isTypingIntroDuration":0,"story":{"__type":"Pointer","className":"Story","objectId":"oKOWCyIHxC"},"risk":2,"createdAt":"2018-06-15T20:52:55.091Z","updatedAt":"2018-06-15T20:52:55.172Z","aclUpdatedAt":{"__type":"Date","iso":"2018-06-15T20:52:55.161Z"},"ACL":{"*":{"read":true},"ODNHPL0tEx":{"write":true}},"objectId":"9HgB8rNnkg","__type":"Object","className":"Message"},{"text":"Are you all right?","ordinalInStory":3,"mediaWidth":null,"mediaHeight":null,"isTypingIntroDuration":0,"sender":{"name":"Jonathan","createdAt":"2018-06-15T20:52:53.009Z","updatedAt":"2018-06-15T20:52:53.009Z","objectId":"6qyHe27abt","__type":"Object","className":"Character"},"story":{"__type":"Pointer","className":"Story","objectId":"oKOWCyIHxC"},"risk":1,"createdAt":"2018-06-15T20:52:55.271Z","updatedAt":"2018-06-15T20:52:55.535Z","aclUpdatedAt":{"__type":"Date","iso":"2018-06-15T20:52:55.324Z"},"ACL":{"*":{"read":true},"ODNHPL0tEx":{"write":true}},"objectId":"qFuka0AINK","__type":"Object","className":"Message"},{"text":"Blake says your bleeding.","ordinalInStory":4,"mediaWidth":null,"mediaHeight":null,"isTypingIntroDuration":0,"sender":{"name":"Jonathan","createdAt":"2018-06-15T20:52:53.009Z","updatedAt":"2018-06-15T20:52:53.009Z","objectId":"6qyHe27abt","__type":"Object","className":"Character"},"story":{"__type":"Pointer","className":"Story","objectId":"oKOWCyIHxC"},"risk":3,"createdAt":"2018-06-15T20:52:55.439Z","updatedAt":"2018-06-15T20:52:55.537Z","aclUpdatedAt":{"__type":"Date","iso":"2018-06-15T20:52:55.527Z"},"ACL":{"*":{"read":true},"ODNHPL0tEx":{"write":true}},"objectId":"lhf4Qu2RAj","__type":"Object","className":"Message"},{"text":"Jesus, please tell me you’re all right.","ordinalInStory":5,"mediaWidth":null,"mediaHeight":null,"isTypingIntroDuration":0,"sender":{"name":"Jonathan","createdAt":"2018-06-15T20:52:53.009Z","updatedAt":"2018-06-15T20:52:53.009Z","objectId":"6qyHe27abt","__type":"Object","className":"Character"},"story":{"__type":"Pointer","className":"Story","objectId":"oKOWCyIHxC"},"risk":3,"createdAt":"2018-06-15T20:52:55.652Z","updatedAt":"2018-06-15T20:52:55.723Z","aclUpdatedAt":{"__type":"Date","iso":"2018-06-15T20:52:55.712Z"},"ACL":{"*":{"read":true},"ODNHPL0tEx":{"write":true}},"objectId":"xCJuXux4GT","__type":"Object","className":"Message"},{"text":"Taylor mutes Jonathan’s texts.","ordinalInStory":6,"mediaWidth":null,"mediaHeight":null,"isTypingIntroDuration":0,"story":{"__type":"Pointer","className":"Story","objectId":"oKOWCyIHxC"},"risk":2,"createdAt":"2018-06-15T20:52:55.818Z","updatedAt":"2018-06-15T20:52:55.895Z","aclUpdatedAt":{"__type":"Date","iso":"2018-06-15T20:52:55.878Z"},"ACL":{"*":{"read":true},"ODNHPL0tEx":{"write":true}},"objectId":"QgIcDgSs6E","__type":"Object","className":"Message"},{"text":"She can’t call her parents, not after what she did.","ordinalInStory":7,"mediaWidth":null,"mediaHeight":null,"isTypingIntroDuration":0,"story":{"__type":"Pointer","className":"Story","objectId":"oKOWCyIHxC"},"risk":2,"createdAt":"2018-06-15T20:52:55.992Z","updatedAt":"2018-06-15T20:52:56.059Z","aclUpdatedAt":{"__type":"Date","iso":"2018-06-15T20:52:56.048Z"},"ACL":{"*":{"read":true},"ODNHPL0tEx":{"write":true}},"objectId":"oaEKvGGGa3","__type":"Object","className":"Message"},{"text":"She can’t talk to Jonathan. Not this time.","ordinalInStory":8,"mediaWidth":null,"mediaHeight":null,"isTypingIntroDuration":0,"story":{"__type":"Pointer","className":"Story","objectId":"oKOWCyIHxC"},"risk":1,"createdAt":"2018-06-15T20:52:56.163Z","updatedAt":"2018-06-15T20:52:56.240Z","aclUpdatedAt":{"__type":"Date","iso":"2018-06-15T20:52:56.218Z"},"ACL":{"*":{"read":true},"ODNHPL0tEx":{"write":true}},"objectId":"HGnLH3CXC0","__type":"Object","className":"Message"},{"text":"Instead, she calls the one person she needs to stop running from.","ordinalInStory":9,"mediaWidth":null,"mediaHeight":null,"isTypingIntroDuration":0,"story":{"__type":"Pointer","className":"Story","objectId":"oKOWCyIHxC"},"risk":2,"createdAt":"2018-06-15T20:52:56.330Z","updatedAt":"2018-06-15T20:52:56.469Z","aclUpdatedAt":{"__type":"Date","iso":"2018-06-15T20:52:56.452Z"},"ACL":{"*":{"read":true},"ODNHPL0tEx":{"write":true}},"objectId":"Kxns6k6Ixh","__type":"Object","className":"Message"},{"text":"I’m coming.","ordinalInStory":10,"mediaWidth":null,"mediaHeight":null,"isTypingIntroDuration":0,"sender":{"name":"Blake","createdAt":"2018-06-15T20:52:53.285Z","updatedAt":"2018-06-15T20:52:53.285Z","objectId":"Mykb1lr5RY","__type":"Object","className":"Character"},"story":{"__type":"Pointer","className":"Story","objectId":"oKOWCyIHxC"},"risk":2,"createdAt":"2018-06-15T20:52:56.557Z","updatedAt":"2018-06-15T20:52:56.620Z","aclUpdatedAt":{"__type":"Date","iso":"2018-06-15T20:52:56.609Z"},"ACL":{"*":{"read":true},"ODNHPL0tEx":{"write":true}},"objectId":"duEAkLE867","__type":"Object","className":"Message"},{"text":"Don’t worry. I’m on my way.","ordinalInStory":11,"mediaWidth":null,"mediaHeight":null,"isTypingIntroDuration":0,"sender":{"name":"Blake","createdAt":"2018-06-15T20:52:53.285Z","updatedAt":"2018-06-15T20:52:53.285Z","objectId":"Mykb1lr5RY","__type":"Object","className":"Character"},"story":{"__type":"Pointer","className":"Story","objectId":"oKOWCyIHxC"},"risk":1,"createdAt":"2018-06-15T20:52:56.727Z","updatedAt":"2018-06-15T20:52:56.799Z","aclUpdatedAt":{"__type":"Date","iso":"2018-06-15T20:52:56.784Z"},"ACL":{"*":{"read":true},"ODNHPL0tEx":{"write":true}},"objectId":"G0n6MHH5kQ","__type":"Object","className":"Message"},{"text":"It’ll take him fifteen minutes to get to the hospital.","ordinalInStory":12,"mediaWidth":null,"mediaHeight":null,"isTypingIntroDuration":0,"story":{"__type":"Pointer","className":"Story","objectId":"oKOWCyIHxC"},"risk":2,"createdAt":"2018-06-15T20:52:56.892Z","updatedAt":"2018-06-15T20:52:56.958Z","aclUpdatedAt":{"__type":"Date","iso":"2018-06-15T20:52:56.948Z"},"ACL":{"*":{"read":true},"ODNHPL0tEx":{"write":true}},"objectId":"2y7FiOeQhW","__type":"Object","className":"Message"},{"text":"Twenty with traffic — and more if he’s far away.","ordinalInStory":13,"mediaWidth":null,"mediaHeight":null,"isTypingIntroDuration":0,"story":{"__type":"Pointer","className":"Story","objectId":"oKOWCyIHxC"},"risk":2,"createdAt":"2018-06-15T20:52:57.055Z","updatedAt":"2018-06-15T20:52:57.121Z","aclUpdatedAt":{"__type":"Date","iso":"2018-06-15T20:52:57.110Z"},"ACL":{"*":{"read":true},"ODNHPL0tEx":{"write":true}},"objectId":"XO3D60St5e","__type":"Object","className":"Message"},{"text":"Taylor looks at the clock. It’s only been seven minutes.","ordinalInStory":14,"mediaWidth":null,"mediaHeight":null,"isTypingIntroDuration":0,"story":{"__type":"Pointer","className":"Story","objectId":"oKOWCyIHxC"},"risk":2,"createdAt":"2018-06-15T20:52:57.218Z","updatedAt":"2018-06-15T20:52:57.273Z","aclUpdatedAt":{"__type":"Date","iso":"2018-06-15T20:52:57.262Z"},"ACL":{"*":{"read":true},"ODNHPL0tEx":{"write":true}},"objectId":"xdQdeJFvGR","__type":"Object","className":"Message"},{"text":"With each breath, fresh tears splatter against the sheets.","ordinalInStory":15,"mediaWidth":null,"mediaHeight":null,"isTypingIntroDuration":0,"story":{"__type":"Pointer","className":"Story","objectId":"oKOWCyIHxC"},"risk":2,"createdAt":"2018-06-15T20:52:57.370Z","updatedAt":"2018-06-15T20:52:57.435Z","aclUpdatedAt":{"__type":"Date","iso":"2018-06-15T20:52:57.425Z"},"ACL":{"*":{"read":true},"ODNHPL0tEx":{"write":true}},"objectId":"UPMA7g6qqU","__type":"Object","className":"Message"},{"text":"She checks the texts she sent Blake.","ordinalInStory":16,"mediaWidth":null,"mediaHeight":null,"isTypingIntroDuration":0,"story":{"__type":"Pointer","className":"Story","objectId":"oKOWCyIHxC"},"risk":2,"createdAt":"2018-06-15T20:52:57.533Z","updatedAt":"2018-06-15T20:52:57.852Z","aclUpdatedAt":{"__type":"Date","iso":"2018-06-15T20:52:57.604Z"},"ACL":{"*":{"read":true},"ODNHPL0tEx":{"write":true}},"objectId":"2vd1FRmaWY","__type":"Object","className":"Message"},{"text":"Room 2126. It’ll be on your right in Labor and Delivery.","ordinalInStory":17,"mediaWidth":null,"mediaHeight":null,"isTypingIntroDuration":0,"sender":{"name":"Taylor","createdAt":"2018-06-15T20:52:53.145Z","updatedAt":"2018-11-15T21:39:57.958Z","main":true,"aclUpdatedAt":{"__type":"Date","iso":"2018-11-15T21:39:57.950Z"},"ACL":{"*":{"read":true},"ODNHPL0tEx":{"write":true}},"objectId":"wpLMHTKAhB","__type":"Object","className":"Character"},"story":{"__type":"Pointer","className":"Story","objectId":"oKOWCyIHxC"},"risk":3,"createdAt":"2018-06-15T20:52:57.715Z","updatedAt":"2018-06-15T20:52:57.793Z","aclUpdatedAt":{"__type":"Date","iso":"2018-06-15T20:52:57.778Z"},"ACL":{"*":{"read":true},"ODNHPL0tEx":{"write":true}},"objectId":"8dLZEqsuJv","__type":"Object","className":"Message"},{"text":"I’m only ten weeks pregnant, Blake — that’s too soon to be here.","ordinalInStory":18,"mediaWidth":null,"mediaHeight":null,"isTypingIntroDuration":0,"sender":{"name":"Taylor","createdAt":"2018-06-15T20:52:53.145Z","updatedAt":"2018-11-15T21:39:57.958Z","main":true,"aclUpdatedAt":{"__type":"Date","iso":"2018-11-15T21:39:57.950Z"},"ACL":{"*":{"read":true},"ODNHPL0tEx":{"write":true}},"objectId":"wpLMHTKAhB","__type":"Object","className":"Character"},"story":{"__type":"Pointer","className":"Story","objectId":"oKOWCyIHxC"},"risk":3,"createdAt":"2018-06-15T20:52:57.879Z","updatedAt":"2018-06-15T20:52:57.944Z","aclUpdatedAt":{"__type":"Date","iso":"2018-06-15T20:52:57.934Z"},"ACL":{"*":{"read":true},"ODNHPL0tEx":{"write":true}},"objectId":"zJM78WOlCu","__type":"Object","className":"Message"},{"text":"The phone buzzes in her hand.","ordinalInStory":19,"mediaWidth":null,"mediaHeight":null,"isTypingIntroDuration":0,"story":{"__type":"Pointer","className":"Story","objectId":"oKOWCyIHxC"},"risk":3,"createdAt":"2018-06-15T20:52:58.039Z","updatedAt":"2018-06-15T20:52:58.144Z","aclUpdatedAt":{"__type":"Date","iso":"2018-06-15T20:52:58.132Z"},"ACL":{"*":{"read":true},"ODNHPL0tEx":{"write":true}},"objectId":"i9AeFxIUdw","__type":"Object","className":"Message"},{"text":"You’re being ridiculous.","ordinalInStory":20,"mediaWidth":null,"mediaHeight":null,"isTypingIntroDuration":0,"sender":{"name":"Mom","createdAt":"2018-06-15T20:52:53.423Z","updatedAt":"2018-06-15T20:52:53.423Z","objectId":"kpAqufNrCW","__type":"Object","className":"Character"},"story":{"__type":"Pointer","className":"Story","objectId":"oKOWCyIHxC"},"risk":2,"createdAt":"2018-06-15T20:52:58.233Z","updatedAt":"2018-06-15T20:52:58.323Z","aclUpdatedAt":{"__type":"Date","iso":"2018-06-15T20:52:58.311Z"},"ACL":{"*":{"read":true},"ODNHPL0tEx":{"write":true}},"objectId":"n5rJCdOhZa","__type":"Object","className":"Message"},{"text":"You’re not a little girl anymore…you can’t just run away.","ordinalInStory":21,"mediaWidth":null,"mediaHeight":null,"isTypingIntroDuration":0,"sender":{"name":"Mom","createdAt":"2018-06-15T20:52:53.423Z","updatedAt":"2018-06-15T20:52:53.423Z","objectId":"kpAqufNrCW","__type":"Object","className":"Character"},"story":{"__type":"Pointer","className":"Story","objectId":"oKOWCyIHxC"},"risk":2,"createdAt":"2018-06-15T20:52:58.413Z","updatedAt":"2018-06-15T20:52:58.561Z","aclUpdatedAt":{"__type":"Date","iso":"2018-06-15T20:52:58.539Z"},"ACL":{"*":{"read":true},"ODNHPL0tEx":{"write":true}},"objectId":"4sPkaRgeyo","__type":"Object","className":"Message"},{"text":"More tears fall, this time faster.","ordinalInStory":22,"mediaWidth":null,"mediaHeight":null,"isTypingIntroDuration":0,"story":{"__type":"Pointer","className":"Story","objectId":"oKOWCyIHxC"},"risk":2,"createdAt":"2018-06-15T20:52:58.656Z","updatedAt":"2018-06-15T20:52:58.714Z","aclUpdatedAt":{"__type":"Date","iso":"2018-06-15T20:52:58.703Z"},"ACL":{"*":{"read":true},"ODNHPL0tEx":{"write":true}},"objectId":"3scDOCHC8M","__type":"Object","className":"Message"},{"text":"Do you have ANY IDEA how much money you wasted?","ordinalInStory":23,"mediaWidth":null,"mediaHeight":null,"isTypingIntroDuration":0,"sender":{"name":"Mom","createdAt":"2018-06-15T20:52:53.423Z","updatedAt":"2018-06-15T20:52:53.423Z","objectId":"kpAqufNrCW","__type":"Object","className":"Character"},"story":{"__type":"Pointer","className":"Story","objectId":"oKOWCyIHxC"},"risk":3,"createdAt":"2018-06-15T20:52:58.810Z","updatedAt":"2018-06-15T20:52:58.901Z","aclUpdatedAt":{"__type":"Date","iso":"2018-06-15T20:52:58.891Z"},"ACL":{"*":{"read":true},"ODNHPL0tEx":{"write":true}},"objectId":"1N88B6tEdq","__type":"Object","className":"Message"},{"text":"Taylor turns off her phone.","ordinalInStory":24,"mediaWidth":null,"mediaHeight":null,"isTypingIntroDuration":0,"story":{"__type":"Pointer","className":"Story","objectId":"oKOWCyIHxC"},"risk":3,"createdAt":"2018-06-15T20:52:59.009Z","updatedAt":"2018-06-15T20:52:59.063Z","aclUpdatedAt":{"__type":"Date","iso":"2018-06-15T20:52:59.051Z"},"ACL":{"*":{"read":true},"ODNHPL0tEx":{"write":true}},"objectId":"WvMQXQ3T2f","__type":"Object","className":"Message"},{"text":"The door crashes open","ordinalInStory":25,"mediaWidth":null,"mediaHeight":null,"isTypingIntroDuration":0,"story":{"__type":"Pointer","className":"Story","objectId":"oKOWCyIHxC"},"risk":2,"createdAt":"2018-06-15T20:52:59.187Z","updatedAt":"2018-06-15T20:52:59.246Z","aclUpdatedAt":{"__type":"Date","iso":"2018-06-15T20:52:59.230Z"},"ACL":{"*":{"read":true},"ODNHPL0tEx":{"write":true}},"objectId":"CHjW8fwtxj","__type":"Object","className":"Message"},{"text":"Hi.","ordinalInStory":26,"mediaWidth":null,"mediaHeight":null,"isTypingIntroDuration":0,"sender":{"name":"Blake","createdAt":"2018-06-15T20:52:53.285Z","updatedAt":"2018-06-15T20:52:53.285Z","objectId":"Mykb1lr5RY","__type":"Object","className":"Character"},"story":{"__type":"Pointer","className":"Story","objectId":"oKOWCyIHxC"},"risk":0,"createdAt":"2018-06-15T20:52:59.353Z","updatedAt":"2018-06-15T20:52:59.556Z","aclUpdatedAt":{"__type":"Date","iso":"2018-06-15T20:52:59.503Z"},"ACL":{"*":{"read":true},"ODNHPL0tEx":{"write":true}},"objectId":"rzWM9AnDBK","__type":"Object","className":"Message"},{"text":"Taylor buries her face in her hands, crying harder.","ordinalInStory":27,"mediaWidth":null,"mediaHeight":null,"isTypingIntroDuration":0,"story":{"__type":"Pointer","className":"Story","objectId":"oKOWCyIHxC"},"risk":2,"createdAt":"2018-06-15T20:52:59.515Z","updatedAt":"2018-06-15T20:52:59.582Z","aclUpdatedAt":{"__type":"Date","iso":"2018-06-15T20:52:59.571Z"},"ACL":{"*":{"read":true},"ODNHPL0tEx":{"write":true}},"objectId":"0VBBAaozaz","__type":"Object","className":"Message"},{"text":"Blake sits on the bed beside her and places his hand gently on her shoulder.","ordinalInStory":28,"mediaWidth":null,"mediaHeight":null,"isTypingIntroDuration":0,"story":{"__type":"Pointer","className":"Story","objectId":"oKOWCyIHxC"},"risk":2,"createdAt":"2018-06-15T20:52:59.681Z","updatedAt":"2018-06-15T20:52:59.748Z","aclUpdatedAt":{"__type":"Date","iso":"2018-06-15T20:52:59.737Z"},"ACL":{"*":{"read":true},"ODNHPL0tEx":{"write":true}},"objectId":"0evmHr1vEB","__type":"Object","className":"Message"},{"text":"It’s bad, isn’t it?","ordinalInStory":29,"mediaWidth":null,"mediaHeight":null,"isTypingIntroDuration":0,"sender":{"name":"Blake","createdAt":"2018-06-15T20:52:53.285Z","updatedAt":"2018-06-15T20:52:53.285Z","objectId":"Mykb1lr5RY","__type":"Object","className":"Character"},"story":{"__type":"Pointer","className":"Story","objectId":"oKOWCyIHxC"},"risk":1,"createdAt":"2018-06-15T20:52:59.866Z","updatedAt":"2018-06-15T20:52:59.990Z","aclUpdatedAt":{"__type":"Date","iso":"2018-06-15T20:52:59.979Z"},"ACL":{"*":{"read":true},"ODNHPL0tEx":{"write":true}},"objectId":"aiwA0FIseW","__type":"Object","className":"Message"},{"text":"Taylor looks up.","ordinalInStory":30,"mediaWidth":null,"mediaHeight":null,"isTypingIntroDuration":0,"story":{"__type":"Pointer","className":"Story","objectId":"oKOWCyIHxC"},"risk":2,"createdAt":"2018-06-15T20:53:00.033Z","updatedAt":"2018-06-15T20:53:00.160Z","aclUpdatedAt":{"__type":"Date","iso":"2018-06-15T20:53:00.149Z"},"ACL":{"*":{"read":true},"ODNHPL0tEx":{"write":true}},"objectId":"F2PceBdPYY","__type":"Object","className":"Message"},{"text":"He’s gone, Blake.","ordinalInStory":31,"mediaWidth":null,"mediaHeight":null,"isTypingIntroDuration":0,"sender":{"name":"Taylor","createdAt":"2018-06-15T20:52:53.145Z","updatedAt":"2018-11-15T21:39:57.958Z","main":true,"aclUpdatedAt":{"__type":"Date","iso":"2018-11-15T21:39:57.950Z"},"ACL":{"*":{"read":true},"ODNHPL0tEx":{"write":true}},"objectId":"wpLMHTKAhB","__type":"Object","className":"Character"},"story":{"__type":"Pointer","className":"Story","objectId":"oKOWCyIHxC"},"risk":2,"createdAt":"2018-06-15T20:53:00.235Z","updatedAt":"2018-06-15T20:53:00.340Z","aclUpdatedAt":{"__type":"Date","iso":"2018-06-15T20:53:00.325Z"},"ACL":{"*":{"read":true},"ODNHPL0tEx":{"write":true}},"objectId":"xJHg3AxQkv","__type":"Object","className":"Message"},{"text":"Our baby is gone.","ordinalInStory":32,"mediaWidth":null,"mediaHeight":null,"isTypingIntroDuration":0,"sender":{"name":"Taylor","createdAt":"2018-06-15T20:52:53.145Z","updatedAt":"2018-11-15T21:39:57.958Z","main":true,"aclUpdatedAt":{"__type":"Date","iso":"2018-11-15T21:39:57.950Z"},"ACL":{"*":{"read":true},"ODNHPL0tEx":{"write":true}},"objectId":"wpLMHTKAhB","__type":"Object","className":"Character"},"story":{"__type":"Pointer","className":"Story","objectId":"oKOWCyIHxC"},"risk":2,"createdAt":"2018-06-15T20:53:00.437Z","updatedAt":"2018-06-15T20:53:00.504Z","aclUpdatedAt":{"__type":"Date","iso":"2018-06-15T20:53:00.485Z"},"ACL":{"*":{"read":true},"ODNHPL0tEx":{"write":true}},"objectId":"CsqG2ygYF3","__type":"Object","className":"Message"},{"text":"How?","ordinalInStory":33,"mediaWidth":null,"mediaHeight":null,"isTypingIntroDuration":0,"sender":{"name":"Blake","createdAt":"2018-06-15T20:52:53.285Z","updatedAt":"2018-06-15T20:52:53.285Z","objectId":"Mykb1lr5RY","__type":"Object","className":"Character"},"story":{"__type":"Pointer","className":"Story","objectId":"oKOWCyIHxC"},"risk":1,"createdAt":"2018-06-15T20:53:00.592Z","updatedAt":"2018-06-15T20:53:00.809Z","aclUpdatedAt":{"__type":"Date","iso":"2018-06-15T20:53:00.774Z"},"ACL":{"*":{"read":true},"ODNHPL0tEx":{"write":true}},"objectId":"CDtxWwj0EQ","__type":"Object","className":"Message"},{"text":"You were doing fine.","ordinalInStory":34,"mediaWidth":null,"mediaHeight":null,"isTypingIntroDuration":0,"sender":{"name":"Blake","createdAt":"2018-06-15T20:52:53.285Z","updatedAt":"2018-06-15T20:52:53.285Z","objectId":"Mykb1lr5RY","__type":"Object","className":"Character"},"story":{"__type":"Pointer","className":"Story","objectId":"oKOWCyIHxC"},"risk":1,"createdAt":"2018-06-15T20:53:00.781Z","updatedAt":"2018-06-15T20:53:01.125Z","aclUpdatedAt":{"__type":"Date","iso":"2018-06-15T20:53:01.112Z"},"ACL":{"*":{"read":true},"ODNHPL0tEx":{"write":true}},"objectId":"j2ZsUYR0ZH","__type":"Object","className":"Message"},{"text":"The doctor says I’m miscarrying.","ordinalInStory":35,"mediaWidth":null,"mediaHeight":null,"isTypingIntroDuration":0,"sender":{"name":"Taylor","createdAt":"2018-06-15T20:52:53.145Z","updatedAt":"2018-11-15T21:39:57.958Z","main":true,"aclUpdatedAt":{"__type":"Date","iso":"2018-11-15T21:39:57.950Z"},"ACL":{"*":{"read":true},"ODNHPL0tEx":{"write":true}},"objectId":"wpLMHTKAhB","__type":"Object","className":"Character"},"story":{"__type":"Pointer","className":"Story","objectId":"oKOWCyIHxC"},"risk":5,"createdAt":"2018-06-15T20:53:01.232Z","updatedAt":"2018-06-15T20:53:01.317Z","aclUpdatedAt":{"__type":"Date","iso":"2018-06-15T20:53:01.307Z"},"ACL":{"*":{"read":true},"ODNHPL0tEx":{"write":true}},"objectId":"lTMMOZvflA","__type":"Object","className":"Message"},{"text":"Your doctor?","ordinalInStory":36,"mediaWidth":null,"mediaHeight":null,"isTypingIntroDuration":0,"sender":{"name":"Blake","createdAt":"2018-06-15T20:52:53.285Z","updatedAt":"2018-06-15T20:52:53.285Z","objectId":"Mykb1lr5RY","__type":"Object","className":"Character"},"story":{"__type":"Pointer","className":"Story","objectId":"oKOWCyIHxC"},"risk":2,"createdAt":"2018-06-15T20:53:01.437Z","updatedAt":"2018-06-15T20:53:01.503Z","aclUpdatedAt":{"__type":"Date","iso":"2018-06-15T20:53:01.494Z"},"ACL":{"*":{"read":true},"ODNHPL0tEx":{"write":true}},"objectId":"RpiNrREAd7","__type":"Object","className":"Message"},{"text":"No. I haven’t seen her.","ordinalInStory":37,"mediaWidth":null,"mediaHeight":null,"isTypingIntroDuration":0,"sender":{"name":"Taylor","createdAt":"2018-06-15T20:52:53.145Z","updatedAt":"2018-11-15T21:39:57.958Z","main":true,"aclUpdatedAt":{"__type":"Date","iso":"2018-11-15T21:39:57.950Z"},"ACL":{"*":{"read":true},"ODNHPL0tEx":{"write":true}},"objectId":"wpLMHTKAhB","__type":"Object","className":"Character"},"story":{"__type":"Pointer","className":"Story","objectId":"oKOWCyIHxC"},"risk":1,"createdAt":"2018-06-15T20:53:01.623Z","updatedAt":"2018-06-15T20:53:01.701Z","aclUpdatedAt":{"__type":"Date","iso":"2018-06-15T20:53:01.690Z"},"ACL":{"*":{"read":true},"ODNHPL0tEx":{"write":true}},"objectId":"INNFvCU6dU","__type":"Object","className":"Message"},{"text":"Then let’s see her.","ordinalInStory":38,"mediaWidth":null,"mediaHeight":null,"isTypingIntroDuration":0,"sender":{"name":"Blake","createdAt":"2018-06-15T20:52:53.285Z","updatedAt":"2018-06-15T20:52:53.285Z","objectId":"Mykb1lr5RY","__type":"Object","className":"Character"},"story":{"__type":"Pointer","className":"Story","objectId":"oKOWCyIHxC"},"risk":1,"createdAt":"2018-06-15T20:53:01.811Z","updatedAt":"2018-06-15T20:53:02.034Z","aclUpdatedAt":{"__type":"Date","iso":"2018-06-15T20:53:01.857Z"},"ACL":{"*":{"read":true},"ODNHPL0tEx":{"write":true}},"objectId":"FUwzXVko8U","__type":"Object","className":"Message"},{"text":"We’ll have her run tests.","ordinalInStory":39,"mediaWidth":null,"mediaHeight":null,"isTypingIntroDuration":0,"sender":{"name":"Blake","createdAt":"2018-06-15T20:52:53.285Z","updatedAt":"2018-06-15T20:52:53.285Z","objectId":"Mykb1lr5RY","__type":"Object","className":"Character"},"story":{"__type":"Pointer","className":"Story","objectId":"oKOWCyIHxC"},"risk":1,"createdAt":"2018-06-15T20:53:01.969Z","updatedAt":"2018-06-15T20:53:02.081Z","aclUpdatedAt":{"__type":"Date","iso":"2018-06-15T20:53:02.020Z"},"ACL":{"*":{"read":true},"ODNHPL0tEx":{"write":true}},"objectId":"VGi2GACJlq","__type":"Object","className":"Message"},{"text":"Whatever it takes.","ordinalInStory":40,"mediaWidth":null,"mediaHeight":null,"isTypingIntroDuration":0,"sender":{"name":"Blake","createdAt":"2018-06-15T20:52:53.285Z","updatedAt":"2018-06-15T20:52:53.285Z","objectId":"Mykb1lr5RY","__type":"Object","className":"Character"},"story":{"__type":"Pointer","className":"Story","objectId":"oKOWCyIHxC"},"risk":2,"createdAt":"2018-06-15T20:53:02.250Z","updatedAt":"2018-06-15T20:53:02.346Z","aclUpdatedAt":{"__type":"Date","iso":"2018-06-15T20:53:02.335Z"},"ACL":{"*":{"read":true},"ODNHPL0tEx":{"write":true}},"objectId":"8lkLKgcWLf","__type":"Object","className":"Message"},{"text":"I’ll pay for it.","ordinalInStory":41,"mediaWidth":null,"mediaHeight":null,"isTypingIntroDuration":0,"sender":{"name":"Blake","createdAt":"2018-06-15T20:52:53.285Z","updatedAt":"2018-06-15T20:52:53.285Z","objectId":"Mykb1lr5RY","__type":"Object","className":"Character"},"story":{"__type":"Pointer","className":"Story","objectId":"oKOWCyIHxC"},"risk":2,"createdAt":"2018-06-15T20:53:02.446Z","updatedAt":"2018-06-15T20:53:02.524Z","aclUpdatedAt":{"__type":"Date","iso":"2018-06-15T20:53:02.511Z"},"ACL":{"*":{"read":true},"ODNHPL0tEx":{"write":true}},"objectId":"YWt8CowqJf","__type":"Object","className":"Message"},{"text":"I’ll take care of everything—","ordinalInStory":42,"mediaWidth":null,"mediaHeight":null,"isTypingIntroDuration":0,"sender":{"name":"Blake","createdAt":"2018-06-15T20:52:53.285Z","updatedAt":"2018-06-15T20:52:53.285Z","objectId":"Mykb1lr5RY","__type":"Object","className":"Character"},"story":{"__type":"Pointer","className":"Story","objectId":"oKOWCyIHxC"},"risk":2,"createdAt":"2018-06-15T20:53:02.625Z","updatedAt":"2018-06-15T20:53:02.698Z","aclUpdatedAt":{"__type":"Date","iso":"2018-06-15T20:53:02.688Z"},"ACL":{"*":{"read":true},"ODNHPL0tEx":{"write":true}},"objectId":"pPUO9FIHBq","__type":"Object","className":"Message"},{"text":"There’s no heartbeat, Blake.","ordinalInStory":43,"mediaWidth":null,"mediaHeight":null,"isTypingIntroDuration":0,"sender":{"name":"Taylor","createdAt":"2018-06-15T20:52:53.145Z","updatedAt":"2018-11-15T21:39:57.958Z","main":true,"aclUpdatedAt":{"__type":"Date","iso":"2018-11-15T21:39:57.950Z"},"ACL":{"*":{"read":true},"ODNHPL0tEx":{"write":true}},"objectId":"wpLMHTKAhB","__type":"Object","className":"Character"},"story":{"__type":"Pointer","className":"Story","objectId":"oKOWCyIHxC"},"risk":2,"createdAt":"2018-06-15T20:53:02.796Z","updatedAt":"2018-06-15T20:53:02.873Z","aclUpdatedAt":{"__type":"Date","iso":"2018-06-15T20:53:02.860Z"},"ACL":{"*":{"read":true},"ODNHPL0tEx":{"write":true}},"objectId":"zdBZFxEwFd","__type":"Object","className":"Message"},{"text":"He’s gone.","ordinalInStory":44,"mediaWidth":null,"mediaHeight":null,"isTypingIntroDuration":0,"sender":{"name":"Taylor","createdAt":"2018-06-15T20:52:53.145Z","updatedAt":"2018-11-15T21:39:57.958Z","main":true,"aclUpdatedAt":{"__type":"Date","iso":"2018-11-15T21:39:57.950Z"},"ACL":{"*":{"read":true},"ODNHPL0tEx":{"write":true}},"objectId":"wpLMHTKAhB","__type":"Object","className":"Character"},"story":{"__type":"Pointer","className":"Story","objectId":"oKOWCyIHxC"},"risk":1,"createdAt":"2018-06-15T20:53:02.967Z","updatedAt":"2018-06-15T20:53:03.037Z","aclUpdatedAt":{"__type":"Date","iso":"2018-06-15T20:53:03.019Z"},"ACL":{"*":{"read":true},"ODNHPL0tEx":{"write":true}},"objectId":"LLw5AHUFbu","__type":"Object","className":"Message"},{"text":"Blake’s hand slips from Taylor’s shoulder.","ordinalInStory":45,"mediaWidth":null,"mediaHeight":null,"isTypingIntroDuration":0,"story":{"__type":"Pointer","className":"Story","objectId":"oKOWCyIHxC"},"risk":2,"createdAt":"2018-06-15T20:53:03.150Z","updatedAt":"2018-06-15T20:53:03.237Z","aclUpdatedAt":{"__type":"Date","iso":"2018-06-15T20:53:03.221Z"},"ACL":{"*":{"read":true},"ODNHPL0tEx":{"write":true}},"objectId":"wLv9ZuvZd0","__type":"Object","className":"Message"},{"text":"He walks toward the window, rubbing his face hard.","ordinalInStory":46,"mediaWidth":null,"mediaHeight":null,"isTypingIntroDuration":0,"story":{"__type":"Pointer","className":"Story","objectId":"oKOWCyIHxC"},"risk":2,"createdAt":"2018-06-15T20:53:03.336Z","updatedAt":"2018-06-15T20:53:03.405Z","aclUpdatedAt":{"__type":"Date","iso":"2018-06-15T20:53:03.394Z"},"ACL":{"*":{"read":true},"ODNHPL0tEx":{"write":true}},"objectId":"NYOv54pDCr","__type":"Object","className":"Message"},{"text":"I’m sorry.","ordinalInStory":47,"mediaWidth":null,"mediaHeight":null,"isTypingIntroDuration":0,"sender":{"name":"Taylor","createdAt":"2018-06-15T20:52:53.145Z","updatedAt":"2018-11-15T21:39:57.958Z","main":true,"aclUpdatedAt":{"__type":"Date","iso":"2018-11-15T21:39:57.950Z"},"ACL":{"*":{"read":true},"ODNHPL0tEx":{"write":true}},"objectId":"wpLMHTKAhB","__type":"Object","className":"Character"},"story":{"__type":"Pointer","className":"Story","objectId":"oKOWCyIHxC"},"risk":1,"createdAt":"2018-06-15T20:53:03.531Z","updatedAt":"2018-06-15T20:53:03.593Z","aclUpdatedAt":{"__type":"Date","iso":"2018-06-15T20:53:03.583Z"},"ACL":{"*":{"read":true},"ODNHPL0tEx":{"write":true}},"objectId":"IkEomWBZuB","__type":"Object","className":"Message"},{"text":"This is my fault.","ordinalInStory":48,"mediaWidth":null,"mediaHeight":null,"isTypingIntroDuration":0,"sender":{"name":"Taylor","createdAt":"2018-06-15T20:52:53.145Z","updatedAt":"2018-11-15T21:39:57.958Z","main":true,"aclUpdatedAt":{"__type":"Date","iso":"2018-11-15T21:39:57.950Z"},"ACL":{"*":{"read":true},"ODNHPL0tEx":{"write":true}},"objectId":"wpLMHTKAhB","__type":"Object","className":"Character"},"story":{"__type":"Pointer","className":"Story","objectId":"oKOWCyIHxC"},"risk":2,"createdAt":"2018-06-15T20:53:03.693Z","updatedAt":"2018-06-15T20:53:03.818Z","aclUpdatedAt":{"__type":"Date","iso":"2018-06-15T20:53:03.754Z"},"ACL":{"*":{"read":true},"ODNHPL0tEx":{"write":true}},"objectId":"jI9cQ4wnzQ","__type":"Object","className":"Message"},{"text":"Blake turns around abruptly.","ordinalInStory":49,"mediaWidth":null,"mediaHeight":null,"isTypingIntroDuration":0,"story":{"__type":"Pointer","className":"Story","objectId":"oKOWCyIHxC"},"risk":2,"createdAt":"2018-06-15T20:53:03.859Z","updatedAt":"2018-06-15T20:53:03.920Z","aclUpdatedAt":{"__type":"Date","iso":"2018-06-15T20:53:03.910Z"},"ACL":{"*":{"read":true},"ODNHPL0tEx":{"write":true}},"objectId":"43VQEELHuh","__type":"Object","className":"Message"},{"text":"Is that what that stupid doctor told you?","ordinalInStory":50,"mediaWidth":null,"mediaHeight":null,"isTypingIntroDuration":0,"sender":{"name":"Blake","createdAt":"2018-06-15T20:52:53.285Z","updatedAt":"2018-06-15T20:52:53.285Z","objectId":"Mykb1lr5RY","__type":"Object","className":"Character"},"story":{"__type":"Pointer","className":"Story","objectId":"oKOWCyIHxC"},"risk":3,"createdAt":"2018-06-15T20:53:04.018Z","updatedAt":"2018-06-15T20:53:04.090Z","aclUpdatedAt":{"__type":"Date","iso":"2018-06-15T20:53:04.078Z"},"ACL":{"*":{"read":true},"ODNHPL0tEx":{"write":true}},"objectId":"M0UUTQ0p5y","__type":"Object","className":"Message"},{"text":"No, it’s what I know.","ordinalInStory":51,"mediaWidth":null,"mediaHeight":null,"isTypingIntroDuration":0,"sender":{"name":"Taylor","createdAt":"2018-06-15T20:52:53.145Z","updatedAt":"2018-11-15T21:39:57.958Z","main":true,"aclUpdatedAt":{"__type":"Date","iso":"2018-11-15T21:39:57.950Z"},"ACL":{"*":{"read":true},"ODNHPL0tEx":{"write":true}},"objectId":"wpLMHTKAhB","__type":"Object","className":"Character"},"story":{"__type":"Pointer","className":"Story","objectId":"oKOWCyIHxC"},"risk":1,"createdAt":"2018-06-15T20:53:04.186Z","updatedAt":"2018-06-15T20:53:04.249Z","aclUpdatedAt":{"__type":"Date","iso":"2018-06-15T20:53:04.238Z"},"ACL":{"*":{"read":true},"ODNHPL0tEx":{"write":true}},"objectId":"gTGNnbsnmt","__type":"Object","className":"Message"},{"text":"How?","ordinalInStory":52,"mediaWidth":null,"mediaHeight":null,"isTypingIntroDuration":0,"sender":{"name":"Blake","createdAt":"2018-06-15T20:52:53.285Z","updatedAt":"2018-06-15T20:52:53.285Z","objectId":"Mykb1lr5RY","__type":"Object","className":"Character"},"story":{"__type":"Pointer","className":"Story","objectId":"oKOWCyIHxC"},"risk":1,"createdAt":"2018-06-15T20:53:04.358Z","updatedAt":"2018-06-15T20:53:04.424Z","aclUpdatedAt":{"__type":"Date","iso":"2018-06-15T20:53:04.410Z"},"ACL":{"*":{"read":true},"ODNHPL0tEx":{"write":true}},"objectId":"n2EkcUyCvT","__type":"Object","className":"Message"},{"text":"What could you possibly have done wrong?","ordinalInStory":53,"mediaWidth":null,"mediaHeight":null,"isTypingIntroDuration":0,"sender":{"name":"Blake","createdAt":"2018-06-15T20:52:53.285Z","updatedAt":"2018-06-15T20:52:53.285Z","objectId":"Mykb1lr5RY","__type":"Object","className":"Character"},"story":{"__type":"Pointer","className":"Story","objectId":"oKOWCyIHxC"},"risk":1,"createdAt":"2018-06-15T20:53:04.520Z","updatedAt":"2018-06-15T20:53:04.591Z","aclUpdatedAt":{"__type":"Date","iso":"2018-06-15T20:53:04.580Z"},"ACL":{"*":{"read":true},"ODNHPL0tEx":{"write":true}},"objectId":"OrtpJ9oDtP","__type":"Object","className":"Message"},{"text":"I ran out of the church, Blake.","ordinalInStory":54,"mediaWidth":null,"mediaHeight":null,"isTypingIntroDuration":0,"sender":{"name":"Taylor","createdAt":"2018-06-15T20:52:53.145Z","updatedAt":"2018-11-15T21:39:57.958Z","main":true,"aclUpdatedAt":{"__type":"Date","iso":"2018-11-15T21:39:57.950Z"},"ACL":{"*":{"read":true},"ODNHPL0tEx":{"write":true}},"objectId":"wpLMHTKAhB","__type":"Object","className":"Character"},"story":{"__type":"Pointer","className":"Story","objectId":"oKOWCyIHxC"},"risk":3,"createdAt":"2018-06-15T20:53:04.689Z","updatedAt":"2018-06-15T20:53:04.758Z","aclUpdatedAt":{"__type":"Date","iso":"2018-06-15T20:53:04.748Z"},"ACL":{"*":{"read":true},"ODNHPL0tEx":{"write":true}},"objectId":"dDKlioeOkf","__type":"Object","className":"Message"},{"text":"I shouldn’t have done that.","ordinalInStory":55,"mediaWidth":null,"mediaHeight":null,"isTypingIntroDuration":0,"sender":{"name":"Taylor","createdAt":"2018-06-15T20:52:53.145Z","updatedAt":"2018-11-15T21:39:57.958Z","main":true,"aclUpdatedAt":{"__type":"Date","iso":"2018-11-15T21:39:57.950Z"},"ACL":{"*":{"read":true},"ODNHPL0tEx":{"write":true}},"objectId":"wpLMHTKAhB","__type":"Object","className":"Character"},"story":{"__type":"Pointer","className":"Story","objectId":"oKOWCyIHxC"},"risk":1,"createdAt":"2018-06-15T20:53:04.864Z","updatedAt":"2018-06-15T20:53:04.924Z","aclUpdatedAt":{"__type":"Date","iso":"2018-06-15T20:53:04.913Z"},"ACL":{"*":{"read":true},"ODNHPL0tEx":{"write":true}},"objectId":"qHbgPhDf4m","__type":"Object","className":"Message"},{"text":"I hurt our baby.","ordinalInStory":56,"mediaWidth":null,"mediaHeight":null,"isTypingIntroDuration":0,"sender":{"name":"Taylor","createdAt":"2018-06-15T20:52:53.145Z","updatedAt":"2018-11-15T21:39:57.958Z","main":true,"aclUpdatedAt":{"__type":"Date","iso":"2018-11-15T21:39:57.950Z"},"ACL":{"*":{"read":true},"ODNHPL0tEx":{"write":true}},"objectId":"wpLMHTKAhB","__type":"Object","className":"Character"},"story":{"__type":"Pointer","className":"Story","objectId":"oKOWCyIHxC"},"risk":2,"createdAt":"2018-06-15T20:53:05.023Z","updatedAt":"2018-06-15T20:53:05.081Z","aclUpdatedAt":{"__type":"Date","iso":"2018-06-15T20:53:05.068Z"},"ACL":{"*":{"read":true},"ODNHPL0tEx":{"write":true}},"objectId":"t99ylvwF6W","__type":"Object","className":"Message"},{"text":"No. Women run during pregnancy all the time.","ordinalInStory":57,"mediaWidth":null,"mediaHeight":null,"isTypingIntroDuration":0,"sender":{"name":"Blake","createdAt":"2018-06-15T20:52:53.285Z","updatedAt":"2018-06-15T20:52:53.285Z","objectId":"Mykb1lr5RY","__type":"Object","className":"Character"},"story":{"__type":"Pointer","className":"Story","objectId":"oKOWCyIHxC"},"risk":3,"createdAt":"2018-06-15T20:53:05.187Z","updatedAt":"2018-06-15T20:53:05.302Z","aclUpdatedAt":{"__type":"Date","iso":"2018-06-15T20:53:05.233Z"},"ACL":{"*":{"read":true},"ODNHPL0tEx":{"write":true}},"objectId":"vFt0VKhgGy","__type":"Object","className":"Message"},{"text":"That one woman ran a marathon pregnant.","ordinalInStory":58,"mediaWidth":null,"mediaHeight":null,"isTypingIntroDuration":0,"sender":{"name":"Blake","createdAt":"2018-06-15T20:52:53.285Z","updatedAt":"2018-06-15T20:52:53.285Z","objectId":"Mykb1lr5RY","__type":"Object","className":"Character"},"story":{"__type":"Pointer","className":"Story","objectId":"oKOWCyIHxC"},"risk":3,"createdAt":"2018-06-15T20:53:05.350Z","updatedAt":"2018-06-15T20:53:05.421Z","aclUpdatedAt":{"__type":"Date","iso":"2018-06-15T20:53:05.409Z"},"ACL":{"*":{"read":true},"ODNHPL0tEx":{"write":true}},"objectId":"94CDfb0DMX","__type":"Object","className":"Message"},{"text":"Those women aren’t me.","ordinalInStory":59,"mediaWidth":null,"mediaHeight":null,"isTypingIntroDuration":0,"sender":{"name":"Taylor","createdAt":"2018-06-15T20:52:53.145Z","updatedAt":"2018-11-15T21:39:57.958Z","main":true,"aclUpdatedAt":{"__type":"Date","iso":"2018-11-15T21:39:57.950Z"},"ACL":{"*":{"read":true},"ODNHPL0tEx":{"write":true}},"objectId":"wpLMHTKAhB","__type":"Object","className":"Character"},"story":{"__type":"Pointer","className":"Story","objectId":"oKOWCyIHxC"},"risk":2,"createdAt":"2018-06-15T20:53:05.531Z","updatedAt":"2018-06-15T20:53:05.579Z","aclUpdatedAt":{"__type":"Date","iso":"2018-06-15T20:53:05.568Z"},"ACL":{"*":{"read":true},"ODNHPL0tEx":{"write":true}},"objectId":"nEHLOObjEE","__type":"Object","className":"Message"},{"text":"I did this — to our baby and to us.","ordinalInStory":60,"mediaWidth":null,"mediaHeight":null,"isTypingIntroDuration":0,"sender":{"name":"Taylor","createdAt":"2018-06-15T20:52:53.145Z","updatedAt":"2018-11-15T21:39:57.958Z","main":true,"aclUpdatedAt":{"__type":"Date","iso":"2018-11-15T21:39:57.950Z"},"ACL":{"*":{"read":true},"ODNHPL0tEx":{"write":true}},"objectId":"wpLMHTKAhB","__type":"Object","className":"Character"},"story":{"__type":"Pointer","className":"Story","objectId":"oKOWCyIHxC"},"risk":2,"createdAt":"2018-06-15T20:53:05.683Z","updatedAt":"2018-06-15T20:53:05.820Z","aclUpdatedAt":{"__type":"Date","iso":"2018-06-15T20:53:05.745Z"},"ACL":{"*":{"read":true},"ODNHPL0tEx":{"write":true}},"objectId":"INVqjSQxZA","__type":"Object","className":"Message"},{"text":"Taylor shifts over when Blake slides into bed with her.","ordinalInStory":61,"mediaWidth":null,"mediaHeight":null,"isTypingIntroDuration":0,"story":{"__type":"Pointer","className":"Story","objectId":"oKOWCyIHxC"},"risk":2,"createdAt":"2018-06-15T20:53:05.854Z","updatedAt":"2018-06-15T20:53:05.915Z","aclUpdatedAt":{"__type":"Date","iso":"2018-06-15T20:53:05.904Z"},"ACL":{"*":{"read":true},"ODNHPL0tEx":{"write":true}},"objectId":"hiLbu18hGu","__type":"Object","className":"Message"},{"text":"For a long few minutes they sit in silence, holding each other and crying softly.","ordinalInStory":62,"mediaWidth":null,"mediaHeight":null,"isTypingIntroDuration":0,"story":{"__type":"Pointer","className":"Story","objectId":"oKOWCyIHxC"},"risk":2,"createdAt":"2018-06-15T20:53:06.016Z","updatedAt":"2018-06-15T20:53:06.084Z","aclUpdatedAt":{"__type":"Date","iso":"2018-06-15T20:53:06.067Z"},"ACL":{"*":{"read":true},"ODNHPL0tEx":{"write":true}},"objectId":"eZRUdHupDz","__type":"Object","className":"Message"},{"text":"I was under a lot of stress these last few days.","ordinalInStory":63,"mediaWidth":null,"mediaHeight":null,"isTypingIntroDuration":0,"sender":{"name":"Taylor","createdAt":"2018-06-15T20:52:53.145Z","updatedAt":"2018-11-15T21:39:57.958Z","main":true,"aclUpdatedAt":{"__type":"Date","iso":"2018-11-15T21:39:57.950Z"},"ACL":{"*":{"read":true},"ODNHPL0tEx":{"write":true}},"objectId":"wpLMHTKAhB","__type":"Object","className":"Character"},"story":{"__type":"Pointer","className":"Story","objectId":"oKOWCyIHxC"},"risk":2,"createdAt":"2018-06-15T20:53:06.175Z","updatedAt":"2018-06-15T20:53:06.236Z","aclUpdatedAt":{"__type":"Date","iso":"2018-06-15T20:53:06.222Z"},"ACL":{"*":{"read":true},"ODNHPL0tEx":{"write":true}},"objectId":"THKZPC9dGp","__type":"Object","className":"Message"},{"text":"Because of the wedding?","ordinalInStory":64,"mediaWidth":null,"mediaHeight":null,"isTypingIntroDuration":0,"sender":{"name":"Blake","createdAt":"2018-06-15T20:52:53.285Z","updatedAt":"2018-06-15T20:52:53.285Z","objectId":"Mykb1lr5RY","__type":"Object","className":"Character"},"story":{"__type":"Pointer","className":"Story","objectId":"oKOWCyIHxC"},"risk":3,"createdAt":"2018-06-15T20:53:06.339Z","updatedAt":"2018-06-15T20:53:06.481Z","aclUpdatedAt":{"__type":"Date","iso":"2018-06-15T20:53:06.471Z"},"ACL":{"*":{"read":true},"ODNHPL0tEx":{"write":true}},"objectId":"txHHCzYM1e","__type":"Object","className":"Message"},{"text":"Or because you were marrying me?","ordinalInStory":65,"mediaWidth":null,"mediaHeight":null,"isTypingIntroDuration":0,"sender":{"name":"Blake","createdAt":"2018-06-15T20:52:53.285Z","updatedAt":"2018-06-15T20:52:53.285Z","objectId":"Mykb1lr5RY","__type":"Object","className":"Character"},"story":{"__type":"Pointer","className":"Story","objectId":"oKOWCyIHxC"},"risk":3,"createdAt":"2018-06-15T20:53:06.596Z","updatedAt":"2018-06-15T20:53:06.651Z","aclUpdatedAt":{"__type":"Date","iso":"2018-06-15T20:53:06.639Z"},"ACL":{"*":{"read":true},"ODNHPL0tEx":{"write":true}},"objectId":"M649jsyWiz","__type":"Object","className":"Message"},{"text":"Blake sighs.","ordinalInStory":66,"mediaWidth":null,"mediaHeight":null,"isTypingIntroDuration":0,"story":{"__type":"Pointer","className":"Story","objectId":"oKOWCyIHxC"},"risk":2,"createdAt":"2018-06-15T20:53:06.759Z","updatedAt":"2018-06-15T20:53:06.819Z","aclUpdatedAt":{"__type":"Date","iso":"2018-06-15T20:53:06.804Z"},"ACL":{"*":{"read":true},"ODNHPL0tEx":{"write":true}},"objectId":"O03AEP27Pb","__type":"Object","className":"Message"},{"text":"It wasn’t supposed to be like this.","ordinalInStory":67,"mediaWidth":null,"mediaHeight":null,"isTypingIntroDuration":0,"sender":{"name":"Blake","createdAt":"2018-06-15T20:52:53.285Z","updatedAt":"2018-06-15T20:52:53.285Z","objectId":"Mykb1lr5RY","__type":"Object","className":"Character"},"story":{"__type":"Pointer","className":"Story","objectId":"oKOWCyIHxC"},"risk":2,"createdAt":"2018-06-15T20:53:06.917Z","updatedAt":"2018-06-15T20:53:06.981Z","aclUpdatedAt":{"__type":"Date","iso":"2018-06-15T20:53:06.967Z"},"ACL":{"*":{"read":true},"ODNHPL0tEx":{"write":true}},"objectId":"jot7z8WOYP","__type":"Object","className":"Message"},{"text":"No, it wasn’t.","ordinalInStory":68,"mediaWidth":null,"mediaHeight":null,"isTypingIntroDuration":0,"sender":{"name":"Taylor","createdAt":"2018-06-15T20:52:53.145Z","updatedAt":"2018-11-15T21:39:57.958Z","main":true,"aclUpdatedAt":{"__type":"Date","iso":"2018-11-15T21:39:57.950Z"},"ACL":{"*":{"read":true},"ODNHPL0tEx":{"write":true}},"objectId":"wpLMHTKAhB","__type":"Object","className":"Character"},"story":{"__type":"Pointer","className":"Story","objectId":"oKOWCyIHxC"},"risk":1,"createdAt":"2018-06-15T20:53:07.074Z","updatedAt":"2018-06-15T20:53:07.122Z","aclUpdatedAt":{"__type":"Date","iso":"2018-06-15T20:53:07.113Z"},"ACL":{"*":{"read":true},"ODNHPL0tEx":{"write":true}},"objectId":"ZTPPlKmyRh","__type":"Object","className":"Message"},{"text":"Jonathan told me he loves you.","ordinalInStory":69,"mediaWidth":null,"mediaHeight":null,"isTypingIntroDuration":0,"sender":{"name":"Blake","createdAt":"2018-06-15T20:52:53.285Z","updatedAt":"2018-06-15T20:52:53.285Z","objectId":"Mykb1lr5RY","__type":"Object","className":"Character"},"story":{"__type":"Pointer","className":"Story","objectId":"oKOWCyIHxC"},"risk":3,"createdAt":"2018-06-15T20:53:07.220Z","updatedAt":"2018-06-15T20:53:07.283Z","aclUpdatedAt":{"__type":"Date","iso":"2018-06-15T20:53:07.270Z"},"ACL":{"*":{"read":true},"ODNHPL0tEx":{"write":true}},"objectId":"4h9UOSnO1F","__type":"Object","className":"Message"},{"text":"Did he tell you?","ordinalInStory":70,"mediaWidth":null,"mediaHeight":null,"isTypingIntroDuration":0,"sender":{"name":"Blake","createdAt":"2018-06-15T20:52:53.285Z","updatedAt":"2018-06-15T20:52:53.285Z","objectId":"Mykb1lr5RY","__type":"Object","className":"Character"},"story":{"__type":"Pointer","className":"Story","objectId":"oKOWCyIHxC"},"risk":1,"createdAt":"2018-06-15T20:53:10.383Z","updatedAt":"2018-06-15T20:53:10.504Z","aclUpdatedAt":{"__type":"Date","iso":"2018-06-15T20:53:10.488Z"},"ACL":{"*":{"read":true},"ODNHPL0tEx":{"write":true}},"objectId":"iNjK2Cycoo","__type":"Object","className":"Message"},{"text":"Yes.","ordinalInStory":71,"mediaWidth":null,"mediaHeight":null,"isTypingIntroDuration":0,"sender":{"name":"Taylor","createdAt":"2018-06-15T20:52:53.145Z","updatedAt":"2018-11-15T21:39:57.958Z","main":true,"aclUpdatedAt":{"__type":"Date","iso":"2018-11-15T21:39:57.950Z"},"ACL":{"*":{"read":true},"ODNHPL0tEx":{"write":true}},"objectId":"wpLMHTKAhB","__type":"Object","className":"Character"},"story":{"__type":"Pointer","className":"Story","objectId":"oKOWCyIHxC"},"risk":1,"createdAt":"2018-06-15T20:53:10.597Z","updatedAt":"2018-06-15T20:53:10.662Z","aclUpdatedAt":{"__type":"Date","iso":"2018-06-15T20:53:10.649Z"},"ACL":{"*":{"read":true},"ODNHPL0tEx":{"write":true}},"objectId":"DgBKLLzyfr","__type":"Object","className":"Message"},{"text":"When?","ordinalInStory":72,"mediaWidth":null,"mediaHeight":null,"isTypingIntroDuration":0,"sender":{"name":"Blake","createdAt":"2018-06-15T20:52:53.285Z","updatedAt":"2018-06-15T20:52:53.285Z","objectId":"Mykb1lr5RY","__type":"Object","className":"Character"},"story":{"__type":"Pointer","className":"Story","objectId":"oKOWCyIHxC"},"risk":1,"createdAt":"2018-06-15T20:53:10.758Z","updatedAt":"2018-06-15T20:53:10.818Z","aclUpdatedAt":{"__type":"Date","iso":"2018-06-15T20:53:10.807Z"},"ACL":{"*":{"read":true},"ODNHPL0tEx":{"write":true}},"objectId":"gErv8lDWq2","__type":"Object","className":"Message"},{"text":"A few days ago.","ordinalInStory":73,"mediaWidth":null,"mediaHeight":null,"isTypingIntroDuration":0,"sender":{"name":"Taylor","createdAt":"2018-06-15T20:52:53.145Z","updatedAt":"2018-11-15T21:39:57.958Z","main":true,"aclUpdatedAt":{"__type":"Date","iso":"2018-11-15T21:39:57.950Z"},"ACL":{"*":{"read":true},"ODNHPL0tEx":{"write":true}},"objectId":"wpLMHTKAhB","__type":"Object","className":"Character"},"story":{"__type":"Pointer","className":"Story","objectId":"oKOWCyIHxC"},"risk":1,"createdAt":"2018-06-15T20:53:10.917Z","updatedAt":"2018-06-15T20:53:10.981Z","aclUpdatedAt":{"__type":"Date","iso":"2018-06-15T20:53:10.965Z"},"ACL":{"*":{"read":true},"ODNHPL0tEx":{"write":true}},"objectId":"i1SaXfuhW4","__type":"Object","className":"Message"},{"text":"Damn it.","ordinalInStory":74,"mediaWidth":null,"mediaHeight":null,"isTypingIntroDuration":0,"sender":{"name":"Blake","createdAt":"2018-06-15T20:52:53.285Z","updatedAt":"2018-06-15T20:52:53.285Z","objectId":"Mykb1lr5RY","__type":"Object","className":"Character"},"story":{"__type":"Pointer","className":"Story","objectId":"oKOWCyIHxC"},"risk":3,"createdAt":"2018-06-15T20:53:11.074Z","updatedAt":"2018-06-15T20:53:11.141Z","aclUpdatedAt":{"__type":"Date","iso":"2018-06-15T20:53:11.123Z"},"ACL":{"*":{"read":true},"ODNHPL0tEx":{"write":true}},"objectId":"XoI36RLUEp","__type":"Object","className":"Message"},{"text":"This isn’t his fault, Blake.","ordinalInStory":75,"mediaWidth":null,"mediaHeight":null,"isTypingIntroDuration":0,"sender":{"name":"Taylor","createdAt":"2018-06-15T20:52:53.145Z","updatedAt":"2018-11-15T21:39:57.958Z","main":true,"aclUpdatedAt":{"__type":"Date","iso":"2018-11-15T21:39:57.950Z"},"ACL":{"*":{"read":true},"ODNHPL0tEx":{"write":true}},"objectId":"wpLMHTKAhB","__type":"Object","className":"Character"},"story":{"__type":"Pointer","className":"Story","objectId":"oKOWCyIHxC"},"risk":2,"createdAt":"2018-06-15T20:53:11.233Z","updatedAt":"2018-06-15T20:53:11.293Z","aclUpdatedAt":{"__type":"Date","iso":"2018-06-15T20:53:11.276Z"},"ACL":{"*":{"read":true},"ODNHPL0tEx":{"write":true}},"objectId":"9TGRBKSw2A","__type":"Object","className":"Message"},{"text":"I don’t know about that.","ordinalInStory":76,"mediaWidth":null,"mediaHeight":null,"isTypingIntroDuration":0,"sender":{"name":"Blake","createdAt":"2018-06-15T20:52:53.285Z","updatedAt":"2018-06-15T20:52:53.285Z","objectId":"Mykb1lr5RY","__type":"Object","className":"Character"},"story":{"__type":"Pointer","className":"Story","objectId":"oKOWCyIHxC"},"risk":1,"createdAt":"2018-06-15T20:53:11.388Z","updatedAt":"2018-06-15T20:53:11.461Z","aclUpdatedAt":{"__type":"Date","iso":"2018-06-15T20:53:11.443Z"},"ACL":{"*":{"read":true},"ODNHPL0tEx":{"write":true}},"objectId":"VmBWClLTQz","__type":"Object","className":"Message"},{"text":"A few minutes pass.","ordinalInStory":77,"mediaWidth":null,"mediaHeight":null,"isTypingIntroDuration":0,"story":{"__type":"Pointer","className":"Story","objectId":"oKOWCyIHxC"},"risk":2,"createdAt":"2018-06-15T20:53:11.552Z","updatedAt":"2018-06-15T20:53:11.603Z","aclUpdatedAt":{"__type":"Date","iso":"2018-06-15T20:53:11.593Z"},"ACL":{"*":{"read":true},"ODNHPL0tEx":{"write":true}},"objectId":"AUOrDxUXYj","__type":"Object","className":"Message"},{"text":"Do you love him?","ordinalInStory":78,"mediaWidth":null,"mediaHeight":null,"isTypingIntroDuration":0,"sender":{"name":"Blake","createdAt":"2018-06-15T20:52:53.285Z","updatedAt":"2018-06-15T20:52:53.285Z","objectId":"Mykb1lr5RY","__type":"Object","className":"Character"},"story":{"__type":"Pointer","className":"Story","objectId":"oKOWCyIHxC"},"risk":3,"createdAt":"2018-06-15T20:53:11.702Z","updatedAt":"2018-06-15T20:53:11.759Z","aclUpdatedAt":{"__type":"Date","iso":"2018-06-15T20:53:11.749Z"},"ACL":{"*":{"read":true},"ODNHPL0tEx":{"write":true}},"objectId":"JpwBFxjYhH","__type":"Object","className":"Message"},{"text":"I’m supposed to love you.","ordinalInStory":79,"mediaWidth":null,"mediaHeight":null,"isTypingIntroDuration":0,"sender":{"name":"Taylor","createdAt":"2018-06-15T20:52:53.145Z","updatedAt":"2018-11-15T21:39:57.958Z","main":true,"aclUpdatedAt":{"__type":"Date","iso":"2018-11-15T21:39:57.950Z"},"ACL":{"*":{"read":true},"ODNHPL0tEx":{"write":true}},"objectId":"wpLMHTKAhB","__type":"Object","className":"Character"},"story":{"__type":"Pointer","className":"Story","objectId":"oKOWCyIHxC"},"risk":3,"createdAt":"2018-06-15T20:53:11.876Z","updatedAt":"2018-06-15T20:53:11.933Z","aclUpdatedAt":{"__type":"Date","iso":"2018-06-15T20:53:11.922Z"},"ACL":{"*":{"read":true},"ODNHPL0tEx":{"write":true}},"objectId":"XHblgc9SA8","__type":"Object","className":"Message"},{"text":"Blake stares at their entwined fingers.","ordinalInStory":80,"mediaWidth":null,"mediaHeight":null,"isTypingIntroDuration":0,"story":{"__type":"Pointer","className":"Story","objectId":"oKOWCyIHxC"},"risk":2,"createdAt":"2018-06-15T20:53:12.027Z","updatedAt":"2018-06-15T20:53:12.088Z","aclUpdatedAt":{"__type":"Date","iso":"2018-06-15T20:53:12.076Z"},"ACL":{"*":{"read":true},"ODNHPL0tEx":{"write":true}},"objectId":"2YWhCcT7bx","__type":"Object","className":"Message"},{"text":"That’s not what I asked.","ordinalInStory":81,"mediaWidth":null,"mediaHeight":null,"isTypingIntroDuration":0,"sender":{"name":"Blake","createdAt":"2018-06-15T20:52:53.285Z","updatedAt":"2018-06-15T20:52:53.285Z","objectId":"Mykb1lr5RY","__type":"Object","className":"Character"},"story":{"__type":"Pointer","className":"Story","objectId":"oKOWCyIHxC"},"risk":1,"createdAt":"2018-06-15T20:53:12.184Z","updatedAt":"2018-06-15T20:53:12.238Z","aclUpdatedAt":{"__type":"Date","iso":"2018-06-15T20:53:12.227Z"},"ACL":{"*":{"read":true},"ODNHPL0tEx":{"write":true}},"objectId":"vKNE8gwucB","__type":"Object","className":"Message"},{"text":"We were supposed to get married.","ordinalInStory":82,"mediaWidth":null,"mediaHeight":null,"isTypingIntroDuration":0,"sender":{"name":"Taylor","createdAt":"2018-06-15T20:52:53.145Z","updatedAt":"2018-11-15T21:39:57.958Z","main":true,"aclUpdatedAt":{"__type":"Date","iso":"2018-11-15T21:39:57.950Z"},"ACL":{"*":{"read":true},"ODNHPL0tEx":{"write":true}},"objectId":"wpLMHTKAhB","__type":"Object","className":"Character"},"story":{"__type":"Pointer","className":"Story","objectId":"oKOWCyIHxC"},"risk":3,"createdAt":"2018-06-15T20:53:12.335Z","updatedAt":"2018-06-15T20:53:12.385Z","aclUpdatedAt":{"__type":"Date","iso":"2018-06-15T20:53:12.375Z"},"ACL":{"*":{"read":true},"ODNHPL0tEx":{"write":true}},"objectId":"aNeFFsRYRJ","__type":"Object","className":"Message"},{"text":"You and I were supposed to make babies.","ordinalInStory":83,"mediaWidth":null,"mediaHeight":null,"isTypingIntroDuration":0,"sender":{"name":"Taylor","createdAt":"2018-06-15T20:52:53.145Z","updatedAt":"2018-11-15T21:39:57.958Z","main":true,"aclUpdatedAt":{"__type":"Date","iso":"2018-11-15T21:39:57.950Z"},"ACL":{"*":{"read":true},"ODNHPL0tEx":{"write":true}},"objectId":"wpLMHTKAhB","__type":"Object","className":"Character"},"story":{"__type":"Pointer","className":"Story","objectId":"oKOWCyIHxC"},"risk":6,"createdAt":"2018-06-15T20:53:12.487Z","updatedAt":"2018-06-15T20:53:12.544Z","aclUpdatedAt":{"__type":"Date","iso":"2018-06-15T20:53:12.529Z"},"ACL":{"*":{"read":true},"ODNHPL0tEx":{"write":true}},"objectId":"06dJ5kQJ2Y","__type":"Object","className":"Message"},{"text":"And live happily ever after, right?","ordinalInStory":84,"mediaWidth":null,"mediaHeight":null,"isTypingIntroDuration":0,"sender":{"name":"Blake","createdAt":"2018-06-15T20:52:53.285Z","updatedAt":"2018-06-15T20:52:53.285Z","objectId":"Mykb1lr5RY","__type":"Object","className":"Character"},"story":{"__type":"Pointer","className":"Story","objectId":"oKOWCyIHxC"},"risk":1,"createdAt":"2018-06-15T20:53:12.639Z","updatedAt":"2018-06-15T20:53:12.694Z","aclUpdatedAt":{"__type":"Date","iso":"2018-06-15T20:53:12.682Z"},"ACL":{"*":{"read":true},"ODNHPL0tEx":{"write":true}},"objectId":"moo5yU7Akf","__type":"Object","className":"Message"},{"text":"That’s what they always told us.","ordinalInStory":85,"mediaWidth":null,"mediaHeight":null,"isTypingIntroDuration":0,"sender":{"name":"Blake","createdAt":"2018-06-15T20:52:53.285Z","updatedAt":"2018-06-15T20:52:53.285Z","objectId":"Mykb1lr5RY","__type":"Object","className":"Character"},"story":{"__type":"Pointer","className":"Story","objectId":"oKOWCyIHxC"},"risk":1,"createdAt":"2018-06-15T20:53:12.792Z","updatedAt":"2018-06-15T20:53:12.853Z","aclUpdatedAt":{"__type":"Date","iso":"2018-06-15T20:53:12.838Z"},"ACL":{"*":{"read":true},"ODNHPL0tEx":{"write":true}},"objectId":"xDWu8LvbMG","__type":"Object","className":"Message"},{"text":"Always.","ordinalInStory":86,"mediaWidth":null,"mediaHeight":null,"isTypingIntroDuration":0,"sender":{"name":"Taylor","createdAt":"2018-06-15T20:52:53.145Z","updatedAt":"2018-11-15T21:39:57.958Z","main":true,"aclUpdatedAt":{"__type":"Date","iso":"2018-11-15T21:39:57.950Z"},"ACL":{"*":{"read":true},"ODNHPL0tEx":{"write":true}},"objectId":"wpLMHTKAhB","__type":"Object","className":"Character"},"story":{"__type":"Pointer","className":"Story","objectId":"oKOWCyIHxC"},"risk":1,"createdAt":"2018-06-15T20:53:12.962Z","updatedAt":"2018-06-15T20:53:13.051Z","aclUpdatedAt":{"__type":"Date","iso":"2018-06-15T20:53:13.036Z"},"ACL":{"*":{"read":true},"ODNHPL0tEx":{"write":true}},"objectId":"Cu0vlzgrn0","__type":"Object","className":"Message"},{"text":"This doesn’t feel so happy.","ordinalInStory":87,"mediaWidth":null,"mediaHeight":null,"isTypingIntroDuration":0,"sender":{"name":"Blake","createdAt":"2018-06-15T20:52:53.285Z","updatedAt":"2018-06-15T20:52:53.285Z","objectId":"Mykb1lr5RY","__type":"Object","className":"Character"},"story":{"__type":"Pointer","className":"Story","objectId":"oKOWCyIHxC"},"risk":1,"createdAt":"2018-06-15T20:53:13.122Z","updatedAt":"2018-06-15T20:53:13.179Z","aclUpdatedAt":{"__type":"Date","iso":"2018-06-15T20:53:13.167Z"},"ACL":{"*":{"read":true},"ODNHPL0tEx":{"write":true}},"objectId":"fJt7D4yHUk","__type":"Object","className":"Message"},{"text":"No, this is as bad is it gets.","ordinalInStory":88,"mediaWidth":null,"mediaHeight":null,"isTypingIntroDuration":0,"sender":{"name":"Taylor","createdAt":"2018-06-15T20:52:53.145Z","updatedAt":"2018-11-15T21:39:57.958Z","main":true,"aclUpdatedAt":{"__type":"Date","iso":"2018-11-15T21:39:57.950Z"},"ACL":{"*":{"read":true},"ODNHPL0tEx":{"write":true}},"objectId":"wpLMHTKAhB","__type":"Object","className":"Character"},"story":{"__type":"Pointer","className":"Story","objectId":"oKOWCyIHxC"},"risk":2,"createdAt":"2018-06-15T20:53:13.275Z","updatedAt":"2018-06-15T20:53:13.336Z","aclUpdatedAt":{"__type":"Date","iso":"2018-06-15T20:53:13.321Z"},"ACL":{"*":{"read":true},"ODNHPL0tEx":{"write":true}},"objectId":"8psS9taeaG","__type":"Object","className":"Message"},{"text":"A minute passes.","ordinalInStory":89,"mediaWidth":null,"mediaHeight":null,"isTypingIntroDuration":0,"story":{"__type":"Pointer","className":"Story","objectId":"oKOWCyIHxC"},"risk":2,"createdAt":"2018-06-15T20:53:13.434Z","updatedAt":"2018-06-15T20:53:13.490Z","aclUpdatedAt":{"__type":"Date","iso":"2018-06-15T20:53:13.478Z"},"ACL":{"*":{"read":true},"ODNHPL0tEx":{"write":true}},"objectId":"drJUFlmhFv","__type":"Object","className":"Message"},{"text":"I didn’t want the baby.","ordinalInStory":90,"mediaWidth":null,"mediaHeight":null,"isTypingIntroDuration":0,"sender":{"name":"Taylor","createdAt":"2018-06-15T20:52:53.145Z","updatedAt":"2018-11-15T21:39:57.958Z","main":true,"aclUpdatedAt":{"__type":"Date","iso":"2018-11-15T21:39:57.950Z"},"ACL":{"*":{"read":true},"ODNHPL0tEx":{"write":true}},"objectId":"wpLMHTKAhB","__type":"Object","className":"Character"},"story":{"__type":"Pointer","className":"Story","objectId":"oKOWCyIHxC"},"risk":2,"createdAt":"2018-06-15T20:53:13.588Z","updatedAt":"2018-06-15T20:53:13.642Z","aclUpdatedAt":{"__type":"Date","iso":"2018-06-15T20:53:13.632Z"},"ACL":{"*":{"read":true},"ODNHPL0tEx":{"write":true}},"objectId":"I9jf5scGhd","__type":"Object","className":"Message"},{"text":"What?","ordinalInStory":91,"mediaWidth":null,"mediaHeight":null,"isTypingIntroDuration":0,"sender":{"name":"Blake","createdAt":"2018-06-15T20:52:53.285Z","updatedAt":"2018-06-15T20:52:53.285Z","objectId":"Mykb1lr5RY","__type":"Object","className":"Character"},"story":{"__type":"Pointer","className":"Story","objectId":"oKOWCyIHxC"},"risk":1,"createdAt":"2018-06-15T20:53:13.745Z","updatedAt":"2018-06-15T20:53:13.839Z","aclUpdatedAt":{"__type":"Date","iso":"2018-06-15T20:53:13.822Z"},"ACL":{"*":{"read":true},"ODNHPL0tEx":{"write":true}},"objectId":"Csw4ERLfJ3","__type":"Object","className":"Message"},{"text":"I mean, I wasn’t ready to be a mother.","ordinalInStory":92,"mediaWidth":null,"mediaHeight":null,"isTypingIntroDuration":0,"sender":{"name":"Taylor","createdAt":"2018-06-15T20:52:53.145Z","updatedAt":"2018-11-15T21:39:57.958Z","main":true,"aclUpdatedAt":{"__type":"Date","iso":"2018-11-15T21:39:57.950Z"},"ACL":{"*":{"read":true},"ODNHPL0tEx":{"write":true}},"objectId":"wpLMHTKAhB","__type":"Object","className":"Character"},"story":{"__type":"Pointer","className":"Story","objectId":"oKOWCyIHxC"},"risk":1,"createdAt":"2018-06-15T20:53:13.932Z","updatedAt":"2018-06-15T20:53:13.998Z","aclUpdatedAt":{"__type":"Date","iso":"2018-06-15T20:53:13.978Z"},"ACL":{"*":{"read":true},"ODNHPL0tEx":{"write":true}},"objectId":"iJ5bgN9tN6","__type":"Object","className":"Message"},{"text":"I wasn’t ready to be a father, either.","ordinalInStory":93,"mediaWidth":null,"mediaHeight":null,"isTypingIntroDuration":0,"sender":{"name":"Blake","createdAt":"2018-06-15T20:52:53.285Z","updatedAt":"2018-06-15T20:52:53.285Z","objectId":"Mykb1lr5RY","__type":"Object","className":"Character"},"story":{"__type":"Pointer","className":"Story","objectId":"oKOWCyIHxC"},"risk":1,"createdAt":"2018-06-15T20:53:14.093Z","updatedAt":"2018-06-15T20:53:14.155Z","aclUpdatedAt":{"__type":"Date","iso":"2018-06-15T20:53:14.140Z"},"ACL":{"*":{"read":true},"ODNHPL0tEx":{"write":true}},"objectId":"eAb2wwjeit","__type":"Object","className":"Message"},{"text":"That doesn’t mean I didn’t love him.","ordinalInStory":94,"mediaWidth":null,"mediaHeight":null,"isTypingIntroDuration":0,"sender":{"name":"Taylor","createdAt":"2018-06-15T20:52:53.145Z","updatedAt":"2018-11-15T21:39:57.958Z","main":true,"aclUpdatedAt":{"__type":"Date","iso":"2018-11-15T21:39:57.950Z"},"ACL":{"*":{"read":true},"ODNHPL0tEx":{"write":true}},"objectId":"wpLMHTKAhB","__type":"Object","className":"Character"},"story":{"__type":"Pointer","className":"Story","objectId":"oKOWCyIHxC"},"risk":3,"createdAt":"2018-06-15T20:53:14.277Z","updatedAt":"2018-06-15T20:53:14.344Z","aclUpdatedAt":{"__type":"Date","iso":"2018-06-15T20:53:14.329Z"},"ACL":{"*":{"read":true},"ODNHPL0tEx":{"write":true}},"objectId":"OLR8SQryRn","__type":"Object","className":"Message"},{"text":"I loved him, too.","ordinalInStory":95,"mediaWidth":null,"mediaHeight":null,"isTypingIntroDuration":0,"sender":{"name":"Blake","createdAt":"2018-06-15T20:52:53.285Z","updatedAt":"2018-06-15T20:52:53.285Z","objectId":"Mykb1lr5RY","__type":"Object","className":"Character"},"story":{"__type":"Pointer","className":"Story","objectId":"oKOWCyIHxC"},"risk":2,"createdAt":"2018-06-15T20:53:14.442Z","updatedAt":"2018-06-15T20:53:14.853Z","aclUpdatedAt":{"__type":"Date","iso":"2018-06-15T20:53:14.842Z"},"ACL":{"*":{"read":true},"ODNHPL0tEx":{"write":true}},"objectId":"5P1dLD2G4p","__type":"Object","className":"Message"},{"text":"Or her.","ordinalInStory":96,"mediaWidth":null,"mediaHeight":null,"isTypingIntroDuration":0,"sender":{"name":"Blake","createdAt":"2018-06-15T20:52:53.285Z","updatedAt":"2018-06-15T20:52:53.285Z","objectId":"Mykb1lr5RY","__type":"Object","className":"Character"},"story":{"__type":"Pointer","className":"Story","objectId":"oKOWCyIHxC"},"risk":1,"createdAt":"2018-06-15T20:53:14.945Z","updatedAt":"2018-06-15T20:53:15.004Z","aclUpdatedAt":{"__type":"Date","iso":"2018-06-15T20:53:14.993Z"},"ACL":{"*":{"read":true},"ODNHPL0tEx":{"write":true}},"objectId":"a0K5paLE13","__type":"Object","className":"Message"},{"text":"Yes, or her.","ordinalInStory":97,"mediaWidth":null,"mediaHeight":null,"isTypingIntroDuration":0,"sender":{"name":"Taylor","createdAt":"2018-06-15T20:52:53.145Z","updatedAt":"2018-11-15T21:39:57.958Z","main":true,"aclUpdatedAt":{"__type":"Date","iso":"2018-11-15T21:39:57.950Z"},"ACL":{"*":{"read":true},"ODNHPL0tEx":{"write":true}},"objectId":"wpLMHTKAhB","__type":"Object","className":"Character"},"story":{"__type":"Pointer","className":"Story","objectId":"oKOWCyIHxC"},"risk":1,"createdAt":"2018-06-15T20:53:15.103Z","updatedAt":"2018-06-15T20:53:15.165Z","aclUpdatedAt":{"__type":"Date","iso":"2018-06-15T20:53:15.146Z"},"ACL":{"*":{"read":true},"ODNHPL0tEx":{"write":true}},"objectId":"hUT6MmwuuD","__type":"Object","className":"Message"},{"text":"Morgan, right, after my grandfather?","ordinalInStory":98,"mediaWidth":null,"mediaHeight":null,"isTypingIntroDuration":0,"sender":{"name":"Blake","createdAt":"2018-06-15T20:52:53.285Z","updatedAt":"2018-06-15T20:52:53.285Z","objectId":"Mykb1lr5RY","__type":"Object","className":"Character"},"story":{"__type":"Pointer","className":"Story","objectId":"oKOWCyIHxC"},"risk":2,"createdAt":"2018-06-15T20:53:15.258Z","updatedAt":"2018-06-15T20:53:15.316Z","aclUpdatedAt":{"__type":"Date","iso":"2018-06-15T20:53:15.306Z"},"ACL":{"*":{"read":true},"ODNHPL0tEx":{"write":true}},"objectId":"OPsCQcieun","__type":"Object","className":"Message"},{"text":"Or Sybil, after my grandmother?","ordinalInStory":99,"mediaWidth":null,"mediaHeight":null,"isTypingIntroDuration":0,"sender":{"name":"Blake","createdAt":"2018-06-15T20:52:53.285Z","updatedAt":"2018-06-15T20:52:53.285Z","objectId":"Mykb1lr5RY","__type":"Object","className":"Character"},"story":{"__type":"Pointer","className":"Story","objectId":"oKOWCyIHxC"},"risk":1,"createdAt":"2018-06-15T20:53:15.415Z","updatedAt":"2018-06-15T20:53:15.486Z","aclUpdatedAt":{"__type":"Date","iso":"2018-06-15T20:53:15.475Z"},"ACL":{"*":{"read":true},"ODNHPL0tEx":{"write":true}},"objectId":"QKc1nXLhll","__type":"Object","className":"Message"},{"text":"Taylor smiles weakly.","ordinalInStory":100,"mediaWidth":null,"mediaHeight":null,"isTypingIntroDuration":0,"story":{"__type":"Pointer","className":"Story","objectId":"oKOWCyIHxC"},"risk":2,"createdAt":"2018-06-15T20:53:15.655Z","updatedAt":"2018-06-15T20:53:15.790Z","aclUpdatedAt":{"__type":"Date","iso":"2018-06-15T20:53:15.779Z"},"ACL":{"*":{"read":true},"ODNHPL0tEx":{"write":true}},"objectId":"pZlID9ySu8","__type":"Object","className":"Message"},{"text":"Those were your names.","ordinalInStory":101,"mediaWidth":null,"mediaHeight":null,"isTypingIntroDuration":0,"sender":{"name":"Taylor","createdAt":"2018-06-15T20:52:53.145Z","updatedAt":"2018-11-15T21:39:57.958Z","main":true,"aclUpdatedAt":{"__type":"Date","iso":"2018-11-15T21:39:57.950Z"},"ACL":{"*":{"read":true},"ODNHPL0tEx":{"write":true}},"objectId":"wpLMHTKAhB","__type":"Object","className":"Character"},"story":{"__type":"Pointer","className":"Story","objectId":"oKOWCyIHxC"},"risk":2,"createdAt":"2018-06-15T20:53:15.813Z","updatedAt":"2018-06-15T20:53:15.905Z","aclUpdatedAt":{"__type":"Date","iso":"2018-06-15T20:53:15.890Z"},"ACL":{"*":{"read":true},"ODNHPL0tEx":{"write":true}},"objectId":"F4HYXoO40x","__type":"Object","className":"Message"},{"text":"I liked Odin and Helena.","ordinalInStory":102,"mediaWidth":null,"mediaHeight":null,"isTypingIntroDuration":0,"sender":{"name":"Taylor","createdAt":"2018-06-15T20:52:53.145Z","updatedAt":"2018-11-15T21:39:57.958Z","main":true,"aclUpdatedAt":{"__type":"Date","iso":"2018-11-15T21:39:57.950Z"},"ACL":{"*":{"read":true},"ODNHPL0tEx":{"write":true}},"objectId":"wpLMHTKAhB","__type":"Object","className":"Character"},"story":{"__type":"Pointer","className":"Story","objectId":"oKOWCyIHxC"},"risk":2,"createdAt":"2018-06-15T20:53:16.008Z","updatedAt":"2018-06-15T20:53:16.152Z","aclUpdatedAt":{"__type":"Date","iso":"2018-06-15T20:53:16.138Z"},"ACL":{"*":{"read":true},"ODNHPL0tEx":{"write":true}},"objectId":"vB4r733P6F","__type":"Object","className":"Message"},{"text":"I didn’t.","ordinalInStory":103,"mediaWidth":null,"mediaHeight":null,"isTypingIntroDuration":0,"sender":{"name":"Blake","createdAt":"2018-06-15T20:52:53.285Z","updatedAt":"2018-06-15T20:52:53.285Z","objectId":"Mykb1lr5RY","__type":"Object","className":"Character"},"story":{"__type":"Pointer","className":"Story","objectId":"oKOWCyIHxC"},"risk":1,"createdAt":"2018-06-15T20:53:16.191Z","updatedAt":"2018-06-15T20:53:16.285Z","aclUpdatedAt":{"__type":"Date","iso":"2018-06-15T20:53:16.266Z"},"ACL":{"*":{"read":true},"ODNHPL0tEx":{"write":true}},"objectId":"gfam0GmsJY","__type":"Object","className":"Message"},{"text":"Both chuckle.","ordinalInStory":104,"mediaWidth":null,"mediaHeight":null,"isTypingIntroDuration":0,"story":{"__type":"Pointer","className":"Story","objectId":"oKOWCyIHxC"},"risk":1,"createdAt":"2018-06-15T20:53:16.344Z","updatedAt":"2018-06-15T20:53:16.415Z","aclUpdatedAt":{"__type":"Date","iso":"2018-06-15T20:53:16.405Z"},"ACL":{"*":{"read":true},"ODNHPL0tEx":{"write":true}},"objectId":"zPuXIzaC3o","__type":"Object","className":"Message"},{"text":"I was sure it was a girl.","ordinalInStory":105,"mediaWidth":null,"mediaHeight":null,"isTypingIntroDuration":0,"sender":{"name":"Blake","createdAt":"2018-06-15T20:52:53.285Z","updatedAt":"2018-06-15T20:52:53.285Z","objectId":"Mykb1lr5RY","__type":"Object","className":"Character"},"story":{"__type":"Pointer","className":"Story","objectId":"oKOWCyIHxC"},"risk":2,"createdAt":"2018-06-15T20:53:16.514Z","updatedAt":"2018-06-15T20:53:16.592Z","aclUpdatedAt":{"__type":"Date","iso":"2018-06-15T20:53:16.577Z"},"ACL":{"*":{"read":true},"ODNHPL0tEx":{"write":true}},"objectId":"eZweft8GlQ","__type":"Object","className":"Message"},{"text":"And I was sure it was a boy.","ordinalInStory":106,"mediaWidth":null,"mediaHeight":null,"isTypingIntroDuration":0,"sender":{"name":"Taylor","createdAt":"2018-06-15T20:52:53.145Z","updatedAt":"2018-11-15T21:39:57.958Z","main":true,"aclUpdatedAt":{"__type":"Date","iso":"2018-11-15T21:39:57.950Z"},"ACL":{"*":{"read":true},"ODNHPL0tEx":{"write":true}},"objectId":"wpLMHTKAhB","__type":"Object","className":"Character"},"story":{"__type":"Pointer","className":"Story","objectId":"oKOWCyIHxC"},"risk":2,"createdAt":"2018-06-15T20:53:16.687Z","updatedAt":"2018-06-15T20:53:16.745Z","aclUpdatedAt":{"__type":"Date","iso":"2018-06-15T20:53:16.730Z"},"ACL":{"*":{"read":true},"ODNHPL0tEx":{"write":true}},"objectId":"GTG4ORB12s","__type":"Object","className":"Message"},{"text":"You were going to be a good dad.","ordinalInStory":107,"mediaWidth":null,"mediaHeight":null,"isTypingIntroDuration":0,"sender":{"name":"Taylor","createdAt":"2018-06-15T20:52:53.145Z","updatedAt":"2018-11-15T21:39:57.958Z","main":true,"aclUpdatedAt":{"__type":"Date","iso":"2018-11-15T21:39:57.950Z"},"ACL":{"*":{"read":true},"ODNHPL0tEx":{"write":true}},"objectId":"wpLMHTKAhB","__type":"Object","className":"Character"},"story":{"__type":"Pointer","className":"Story","objectId":"oKOWCyIHxC"},"risk":1,"createdAt":"2018-06-15T20:53:16.844Z","updatedAt":"2018-06-15T20:53:16.923Z","aclUpdatedAt":{"__type":"Date","iso":"2018-06-15T20:53:16.913Z"},"ACL":{"*":{"read":true},"ODNHPL0tEx":{"write":true}},"objectId":"cRnydUtyKj","__type":"Object","className":"Message"},{"text":"And you a great mom.","ordinalInStory":108,"mediaWidth":null,"mediaHeight":null,"isTypingIntroDuration":0,"sender":{"name":"Blake","createdAt":"2018-06-15T20:52:53.285Z","updatedAt":"2018-06-15T20:52:53.285Z","objectId":"Mykb1lr5RY","__type":"Object","className":"Character"},"story":{"__type":"Pointer","className":"Story","objectId":"oKOWCyIHxC"},"risk":1,"createdAt":"2018-06-15T20:53:17.034Z","updatedAt":"2018-06-15T20:53:17.268Z","aclUpdatedAt":{"__type":"Date","iso":"2018-06-15T20:53:17.257Z"},"ACL":{"*":{"read":true},"ODNHPL0tEx":{"write":true}},"objectId":"sgyl4KmmAR","__type":"Object","className":"Message"},{"text":"Maybe…","ordinalInStory":109,"mediaWidth":null,"mediaHeight":null,"isTypingIntroDuration":0,"sender":{"name":"Taylor","createdAt":"2018-06-15T20:52:53.145Z","updatedAt":"2018-11-15T21:39:57.958Z","main":true,"aclUpdatedAt":{"__type":"Date","iso":"2018-11-15T21:39:57.950Z"},"ACL":{"*":{"read":true},"ODNHPL0tEx":{"write":true}},"objectId":"wpLMHTKAhB","__type":"Object","className":"Character"},"story":{"__type":"Pointer","className":"Story","objectId":"oKOWCyIHxC"},"risk":1,"createdAt":"2018-06-15T20:53:17.381Z","updatedAt":"2018-06-15T20:53:17.443Z","aclUpdatedAt":{"__type":"Date","iso":"2018-06-15T20:53:17.426Z"},"ACL":{"*":{"read":true},"ODNHPL0tEx":{"write":true}},"objectId":"hK4UgvrSqK","__type":"Object","className":"Message"},{"text":"There’s no maybe.","ordinalInStory":110,"mediaWidth":null,"mediaHeight":null,"isTypingIntroDuration":0,"sender":{"name":"Blake","createdAt":"2018-06-15T20:52:53.285Z","updatedAt":"2018-06-15T20:52:53.285Z","objectId":"Mykb1lr5RY","__type":"Object","className":"Character"},"story":{"__type":"Pointer","className":"Story","objectId":"oKOWCyIHxC"},"risk":1,"createdAt":"2018-06-15T20:53:17.534Z","updatedAt":"2018-06-15T20:53:17.600Z","aclUpdatedAt":{"__type":"Date","iso":"2018-06-15T20:53:17.582Z"},"ACL":{"*":{"read":true},"ODNHPL0tEx":{"write":true}},"objectId":"LwsBEH2TPh","__type":"Object","className":"Message"},{"text":"You’re the best person I know.","ordinalInStory":111,"mediaWidth":null,"mediaHeight":null,"isTypingIntroDuration":0,"sender":{"name":"Blake","createdAt":"2018-06-15T20:52:53.285Z","updatedAt":"2018-06-15T20:52:53.285Z","objectId":"Mykb1lr5RY","__type":"Object","className":"Character"},"story":{"__type":"Pointer","className":"Story","objectId":"oKOWCyIHxC"},"risk":1,"createdAt":"2018-06-15T20:53:17.684Z","updatedAt":"2018-06-15T20:53:17.750Z","aclUpdatedAt":{"__type":"Date","iso":"2018-06-15T20:53:17.737Z"},"ACL":{"*":{"read":true},"ODNHPL0tEx":{"write":true}},"objectId":"ylynViyJaG","__type":"Object","className":"Message"},{"text":"I wish I could believe you.","ordinalInStory":112,"mediaWidth":null,"mediaHeight":null,"isTypingIntroDuration":0,"sender":{"name":"Taylor","createdAt":"2018-06-15T20:52:53.145Z","updatedAt":"2018-11-15T21:39:57.958Z","main":true,"aclUpdatedAt":{"__type":"Date","iso":"2018-11-15T21:39:57.950Z"},"ACL":{"*":{"read":true},"ODNHPL0tEx":{"write":true}},"objectId":"wpLMHTKAhB","__type":"Object","className":"Character"},"story":{"__type":"Pointer","className":"Story","objectId":"oKOWCyIHxC"},"risk":1,"createdAt":"2018-06-15T20:53:17.844Z","updatedAt":"2018-06-15T20:53:17.904Z","aclUpdatedAt":{"__type":"Date","iso":"2018-06-15T20:53:17.895Z"},"ACL":{"*":{"read":true},"ODNHPL0tEx":{"write":true}},"objectId":"Kxt7Ly8D1W","__type":"Object","className":"Message"},{"text":"Just like I wish I could believe in us.","ordinalInStory":113,"mediaWidth":null,"mediaHeight":null,"isTypingIntroDuration":0,"sender":{"name":"Taylor","createdAt":"2018-06-15T20:52:53.145Z","updatedAt":"2018-11-15T21:39:57.958Z","main":true,"aclUpdatedAt":{"__type":"Date","iso":"2018-11-15T21:39:57.950Z"},"ACL":{"*":{"read":true},"ODNHPL0tEx":{"write":true}},"objectId":"wpLMHTKAhB","__type":"Object","className":"Character"},"story":{"__type":"Pointer","className":"Story","objectId":"oKOWCyIHxC"},"risk":2,"createdAt":"2018-06-15T20:53:18.014Z","updatedAt":"2018-06-15T20:53:18.094Z","aclUpdatedAt":{"__type":"Date","iso":"2018-06-15T20:53:18.071Z"},"ACL":{"*":{"read":true},"ODNHPL0tEx":{"write":true}},"objectId":"SXbYO3rcOe","__type":"Object","className":"Message"},{"text":"Are you saying that because I’ve cheated?","ordinalInStory":114,"mediaWidth":null,"mediaHeight":null,"isTypingIntroDuration":0,"sender":{"name":"Blake","createdAt":"2018-06-15T20:52:53.285Z","updatedAt":"2018-06-15T20:52:53.285Z","objectId":"Mykb1lr5RY","__type":"Object","className":"Character"},"story":{"__type":"Pointer","className":"Story","objectId":"oKOWCyIHxC"},"risk":2,"createdAt":"2018-06-15T20:53:18.186Z","updatedAt":"2018-06-15T20:53:18.282Z","aclUpdatedAt":{"__type":"Date","iso":"2018-06-15T20:53:18.263Z"},"ACL":{"*":{"read":true},"ODNHPL0tEx":{"write":true}},"objectId":"7EBj7HasF6","__type":"Object","className":"Message"},{"text":"It’s okay. I know you know.","ordinalInStory":115,"mediaWidth":null,"mediaHeight":null,"isTypingIntroDuration":0,"sender":{"name":"Blake","createdAt":"2018-06-15T20:52:53.285Z","updatedAt":"2018-06-15T20:52:53.285Z","objectId":"Mykb1lr5RY","__type":"Object","className":"Character"},"story":{"__type":"Pointer","className":"Story","objectId":"oKOWCyIHxC"},"risk":1,"createdAt":"2018-06-15T20:53:18.373Z","updatedAt":"2018-06-15T20:53:18.436Z","aclUpdatedAt":{"__type":"Date","iso":"2018-06-15T20:53:18.426Z"},"ACL":{"*":{"read":true},"ODNHPL0tEx":{"write":true}},"objectId":"ADXeM4SDYq","__type":"Object","className":"Message"},{"text":"Taylor wipes her eyes.","ordinalInStory":116,"mediaWidth":null,"mediaHeight":null,"isTypingIntroDuration":0,"story":{"__type":"Pointer","className":"Story","objectId":"oKOWCyIHxC"},"risk":2,"createdAt":"2018-06-15T20:53:18.533Z","updatedAt":"2018-06-15T20:53:18.625Z","aclUpdatedAt":{"__type":"Date","iso":"2018-06-15T20:53:18.614Z"},"ACL":{"*":{"read":true},"ODNHPL0tEx":{"write":true}},"objectId":"djR3Clc7Oi","__type":"Object","className":"Message"},{"text":"I wanted to be good enough for you.","ordinalInStory":117,"mediaWidth":null,"mediaHeight":null,"isTypingIntroDuration":0,"sender":{"name":"Taylor","createdAt":"2018-06-15T20:52:53.145Z","updatedAt":"2018-11-15T21:39:57.958Z","main":true,"aclUpdatedAt":{"__type":"Date","iso":"2018-11-15T21:39:57.950Z"},"ACL":{"*":{"read":true},"ODNHPL0tEx":{"write":true}},"objectId":"wpLMHTKAhB","__type":"Object","className":"Character"},"story":{"__type":"Pointer","className":"Story","objectId":"oKOWCyIHxC"},"risk":1,"createdAt":"2018-06-15T20:53:18.733Z","updatedAt":"2018-06-15T20:53:18.800Z","aclUpdatedAt":{"__type":"Date","iso":"2018-06-15T20:53:18.788Z"},"ACL":{"*":{"read":true},"ODNHPL0tEx":{"write":true}},"objectId":"ZlOTrmCcV3","__type":"Object","className":"Message"},{"text":"You are, Tay. If anything, you’re TOO good.","ordinalInStory":118,"mediaWidth":null,"mediaHeight":null,"isTypingIntroDuration":0,"sender":{"name":"Blake","createdAt":"2018-06-15T20:52:53.285Z","updatedAt":"2018-06-15T20:52:53.285Z","objectId":"Mykb1lr5RY","__type":"Object","className":"Character"},"story":{"__type":"Pointer","className":"Story","objectId":"oKOWCyIHxC"},"risk":1,"createdAt":"2018-06-15T20:53:18.917Z","updatedAt":"2018-06-15T20:53:18.985Z","aclUpdatedAt":{"__type":"Date","iso":"2018-06-15T20:53:18.969Z"},"ACL":{"*":{"read":true},"ODNHPL0tEx":{"write":true}},"objectId":"sw816RWn5h","__type":"Object","className":"Message"},{"text":"Then why did you cheat?","ordinalInStory":119,"mediaWidth":null,"mediaHeight":null,"isTypingIntroDuration":0,"sender":{"name":"Taylor","createdAt":"2018-06-15T20:52:53.145Z","updatedAt":"2018-11-15T21:39:57.958Z","main":true,"aclUpdatedAt":{"__type":"Date","iso":"2018-11-15T21:39:57.950Z"},"ACL":{"*":{"read":true},"ODNHPL0tEx":{"write":true}},"objectId":"wpLMHTKAhB","__type":"Object","className":"Character"},"story":{"__type":"Pointer","className":"Story","objectId":"oKOWCyIHxC"},"risk":2,"createdAt":"2018-06-15T20:53:19.087Z","updatedAt":"2018-06-15T20:53:19.154Z","aclUpdatedAt":{"__type":"Date","iso":"2018-06-15T20:53:19.132Z"},"ACL":{"*":{"read":true},"ODNHPL0tEx":{"write":true}},"objectId":"4ldxeHYLwC","__type":"Object","className":"Message"},{"text":"Just because I cheated, doesn’t mean that I don’t love you.","ordinalInStory":120,"mediaWidth":null,"mediaHeight":null,"isTypingIntroDuration":0,"sender":{"name":"Blake","createdAt":"2018-06-15T20:52:53.285Z","updatedAt":"2018-06-15T20:52:53.285Z","objectId":"Mykb1lr5RY","__type":"Object","className":"Character"},"story":{"__type":"Pointer","className":"Story","objectId":"oKOWCyIHxC"},"risk":3,"createdAt":"2018-06-15T20:53:19.257Z","updatedAt":"2018-06-15T20:53:19.323Z","aclUpdatedAt":{"__type":"Date","iso":"2018-06-15T20:53:19.308Z"},"ACL":{"*":{"read":true},"ODNHPL0tEx":{"write":true}},"objectId":"VtwGdyDTfB","__type":"Object","className":"Message"},{"text":"Blake kisses Taylor’s lips tenderly.","ordinalInStory":121,"mediaWidth":null,"mediaHeight":null,"isTypingIntroDuration":0,"story":{"__type":"Pointer","className":"Story","objectId":"oKOWCyIHxC"},"risk":3,"createdAt":"2018-06-15T20:53:19.417Z","updatedAt":"2018-06-15T20:53:19.482Z","aclUpdatedAt":{"__type":"Date","iso":"2018-06-15T20:53:19.469Z"},"ACL":{"*":{"read":true},"ODNHPL0tEx":{"write":true}},"objectId":"Lfb5mBTl2Q","__type":"Object","className":"Message"},{"text":"I just haven’t loved you enough.","ordinalInStory":122,"mediaWidth":null,"mediaHeight":null,"isTypingIntroDuration":0,"sender":{"name":"Blake","createdAt":"2018-06-15T20:52:53.285Z","updatedAt":"2018-06-15T20:52:53.285Z","objectId":"Mykb1lr5RY","__type":"Object","className":"Character"},"story":{"__type":"Pointer","className":"Story","objectId":"oKOWCyIHxC"},"risk":2,"createdAt":"2018-06-15T20:53:19.575Z","updatedAt":"2018-06-15T20:53:19.631Z","aclUpdatedAt":{"__type":"Date","iso":"2018-06-15T20:53:19.621Z"},"ACL":{"*":{"read":true},"ODNHPL0tEx":{"write":true}},"objectId":"iU4VFjnIss","__type":"Object","className":"Message"}]}}